Workbook
Name _GoBack: 填表说明!#REF!

Sheet 填表说明
A2: 一、 填写规则
A3: 1. “ICT类项目财务价值评估表”共3部分，项目概况、基础数据和效益评估。该表格有自动计算公式，只需填写标黄部分的单元格，严禁修改橙色内容，金额数据单位为万元。
A4: 2. 首先填写项目基本信息
A5: 3.在“基础数据”部分，根据项目情况填写投资、收入、成本细项含税金额及对应税率，税率为经验参考值，可根据项目实际情况进行修正。若某单项指标可能涉及到多种增值税率，在表中无法准确计算出不含税的数据，可直接将结果填写在表中相应位置，模板自动计算不含税金额。
A6: 4. 在“经济效益评估”中，填写的数据均为不含税金额 （1）“初始项目投资”即使用ICT切块资金金额，按照实际使用投资按年度分别填写； （2）“收入”包含该项目直接收益的各项业务年收入累计值，按照实际收入协议期每年列支金额分别填写； （3）“支出”包含业务维护成本和IT建设成本，业务成本即使用合作模式和购销模式使用的成本费用； （4）“终端及其他营销资源投入”包含用于该项目营销成本、终端、酬金等其它营销资源等。 （5）对填列金额与基础数据在M列设置校验关系，校验结果应为“TRUE”
A7: 5.折旧和摊销计算表见附表，需填列各类资产投资额及投产月份，表格自动计算折旧额。
A8: 二、 重要指标说明
A9: 1. 财务净现值率=净现值/项目总投入现值*100%，净现值为建设期及生产期各年净现金流量现值合计值，总投入现值为建设及生产期内的建设投资及成本支出的累计现值。
A10: 2.静态投资回收期=不考虑时间价值，累计净现金流量开始出现正值的年份数-1+上一年累计净现金流量的绝对值/出现正值年份的净现金流量。
A11: 3. 动态投资回收期=考虑时间价值，累计净现值开始出现正值的年份数-1+上一年累计净现值的绝对值/出现正值年份的净现值。
A12: 4. 折现率参考通信行业折现率，本表中取国资委给定的公司加权平均资本成本（目前为5.5%）。
A13: 5. 折旧及摊销费，根据各年项目投资计算各年的折旧费，采用平均年限法计算折旧，按照中国移动固定资产目录，光缆和管道按照10年、传输设备7年、服务器5年计算折旧。
... A15: 7. 在本表中仅考虑项目建设开展过程中的直接成本，因间接成本项较多，难以准确计算，且在计算效益时影响相对较小，故在本表中未纳入计算，但应对投资效益从严把控。

Sheet 政企项目投资效益评估表
A1: ICT类项目财务价值评估表
A2: 本模板适用于合作模式、投资模式和其它模式投资部分，并适用于以上各模式混合的项目
A3: 项目概况 | B3: 项目名称 | D3: 综合布线及无线网络建设项目 | F3: 业主单位 | G3: 有研亿金新材料（山东）有限公司
B4: 项目年限 | D4: 1 | F4: 预计投资金额 | G4: =H31-J31-K31 -> 0 | H4: 预计收入金额 | I4: =H17-J17-K17 -> 16.772251 | J4: 预计成本金额 | K4: =H49-J49-K49 -> 14.955802
A6: 基础数据 | B6: 明细项目（单位：万元） | F6: CT（含税） | G6: IT（含税） | H6: 合同金额（含税） | I6: 税率 | J6: CT增值税 | K6: IT增值税 | L6: 备注
A7: 直接收入 | B7: 项目收入 （万元） | C7: 1）集成费 | G7: 7.91 | H7: =F7+G7 -> 7.91 | I7: 0.06 | J7: =F7/(1+I7)*I7 -> 0 | K7: =G7/(1+I7)*I7 -> 0.44773585 | L7: 根据客户的需求，将硬件、网络、数据库及相应的应用软件进行优化整合，提供全面系统解决方案而向客户收取的系统集成费，主要包括项目集成方案的咨询、设计、软硬件安装、通信工程服务、调测开通等项目实施服务费，为一次性费用。
C8: 2）维保费 | H8: =F8+G8 -> 0 | I8: 0.06 | J8: =F8/(1+I8)*I8 -> 0 | K8: =G8/(1+I8)*I8 -> 0 | L8: 指公司在ICT项目建成后，因提供后续维护保障服务而向客户收取的维保费。
C9: 3）通信业务收入（基础电信服务） | H9: =F9+G9 -> 0 | I9: 0.09 | J9: =F9/(1+I9)*I9 -> 0 | K9: =G9/(1+I9)*I9 -> 0 | L9: 指ICT项目建成后客户使用ICT业务而产生的语音、短彩信、无线上网、专线、物联网等通信服务费。
C10: 4）通信业务收入（增值电信服务） | H10: =F10+G10 -> 0 | I10: 0.06 | J10: =F10/(1+I10)*I10 -> 0 | K10: =G10/(1+I10)*I10 -> 0 | L10: 指ICT项目建成后客户使用ICT业务而产生的互联网业务等通信服务费。
C11: 5）功能费收入 | H11: =F11+G11 -> 0 | I11: 0.06 | J11: =F11/(1+I11)*I11 -> 0 | K11: =G11/(1+I11)*I11 -> 0 | L11: 指标准化集团信息化产品按月产生的功能费收入，如视频监控等。
C12: 6）设备租赁收入 | H12: =F12+G12 -> 0 | I12: 0.13 | J12: =F12/(1+I12)*I12 -> 0 | K12: =G12/(1+I12)*I12 -> 0 | L12: 指ICT项目中出租设备产生的收入。
C13: 7）设备（含第三方软件）销售收入 | H13: =F13+G13 -> 0 | I13: 0.13 | J13: =F13/(1+I13)*I13 -> 0 | K13: =G13/(1+I13)*I13 -> 0 | L13: 指ICT项目中销售设备及相关第三方软件产生的收入。
C14: 8）终端（含第三方软件）销售收入 | H14: =F14+G14 -> 0 | I14: 0.13 | J14: =F14/(1+I14)*I14 -> 0 | K14: =G14/(1+I14)*I14 -> 0 | L14: 指ICT项目中销售终端及相关第三方软件产生的收入。
C15: 9）终端租赁收入 | H15: =F15+G15 -> 0 | I15: 0.13 | J15: =F15/(1+I15)*I15 -> 0 | K15: =G15/(1+I15)*I15 -> 0 | L15: 指ICT项目中出租终端产生的收入。
C16: 10）其他收入 | G16: 10.147886 | H16: =F16+G16 -> 10.147886 | I16: 0.09 | J16: =F16/(1+I16)*I16 -> 0 | K16: =G16/(1+I16)*I16 -> 0.83789884 | L16: 指项目带来的其他收入 | P16: 0.196 | Q16: 9.95 | R16: =P16+Q16 -> 10.146
B17: 项目收入小计 | F17: =SUM(F7:F16) -> 0 | G17: =SUM(G7:G16) -> 18.057886 | H17: =F17+G17 -> 18.057886 | J17: =SUM(J7:J16) -> 0 | K17: =SUM(K7:K16) -> 1.2856347
A18: 直接支出 | B18: 投资 （万元） | C18: 其中：1、平台类投资 | F18: =SUM(F19:F24) -> 0 | G18: =SUM(G19:G24) -> 0 | H18: =F18+G18 -> 0 | J18: =SUM(J19:J24) -> 0 | K18: =SUM(K19:K24) -> 0
C19: 1）硬件设备类投资 | H19: =F19+G19 -> 0 | I19: 0.13 | J19: =F19/(1+I19)*I19 -> 0 | K19: =G19/(1+I19)*I19 -> 0 | L19: 指项目建设完成后资产归属于我公司的平台设备采购投资。
C20: 2）定制软件类投资 | H20: =F20+G20 -> 0 | I20: 0.06 | J20: =F20/(1+I20)*I20 -> 0 | K20: =G20/(1+I20)*I20 -> 0 | L20: 指项目建设完成后资产归属于我公司的平台定制软件采购投资。
C21: 3）集成服务费 | H21: =F21+G21 -> 0 | I21: 0.06 | J21: =F21/(1+I21)*I21 -> 0 | K21: =G21/(1+I21)*I21 -> 0 | L21: 指资产归属于我公司的平台软硬件设备集成费用。
C22: 4）工程配套费 | H22: =F22+G22 -> 0 | J22: =F22/(1+I22)*I22 -> 0 | K22: =G22/(1+I22)*I22 -> 0 | L22: 指资产归属我公司的平台软硬件设备设所需的线缆、走线架等配套费用
C23: 5）建安费用 | H23: =F23+G23 -> 0 | J23: =F23/(1+I23)*I23 -> 0 | K23: =G23/(1+I23)*I23 -> 0 | L23: 指资产归属我公司的平台软硬件设备建设安装工程费。
C24: 6）设计监理费 | H24: =F24+G24 -> 0 | I24: 0.06 | J24: =F24/(1+I24)*I24 -> 0 | K24: =G24/(1+I24)*I24 -> 0 | L24: 指项目建设完成后资产归属于我公司投资项目相关的设计、可研及监理费用。
C25: 2、传输网络配套投资 | F25: =SUM(F26:F28) -> 0 | G25: =SUM(G26:G28) -> 0 | H25: =F25+G25 -> 0 | J25: =SUM(J26:J28) -> 0 | K25: =SUM(K26:K28) -> 0
C26: 1）管道类投资 | H26: =F26+G26 -> 0 | I26: 0.13 | J26: =F26/(1+I26)*I26 -> 0 | K26: =G26/(1+I26)*I26 -> 0 | L26: 指项目建设末端接入需要的管道、杆路等主材、配套和工程服务投资。
C27: 2）光缆类投资 | H27: =F27+G27 -> 0 | I27: 0.13 | J27: =F27/(1+I27)*I27 -> 0 | K27: =G27/(1+I27)*I27 -> 0 | L27: 指项目建设末端接入需要的光缆等主材、配套和工程服务投资。 | P27: =Q56 -> 0.081225634
C28: 3）设备类投资 | H28: =F28+G28 -> 0 | I28: 0.13 | J28: =F28/(1+I28)*I28 -> 0 | K28: =G28/(1+I28)*I28 -> 0 | L28: 指项目建设末端接入需要的SDH/PTN/OTN/GPON/微波以及MSAP，小型化PTN、光收发、协转、OLP、IMS接入设备等主设备、配套和工程服务投资。 | P28: =Q57 -> 0.088406508
C29: 3、其他网络配套投资 | F29: =SUM(F30) -> 0 | G29: =SUM(G30) -> 0 | H29: =F29+G29 -> 0 | J29: =SUM(J30) -> 0 | K29: =SUM(K30) -> 0 | L29: 项目建设中涉及的其他网络配套投资。
C30: 其他建设费用（如有需按税率区分） | H30: =F30+G30 -> 0 | J30: =F30/(1+I30)*I30 -> 0 | K30: =G30/(1+I30)*I30 -> 0 | L30: 项目建设中涉及的其他网络配套投资。
B31: 投资小计 | F31: =F18+F25+F29 -> 0 | G31: =G18+G25+G29 -> 0 | H31: =F31+G31 -> 0 | J31: =J18+J25+J29 -> 0 | K31: =K18+K25+K29 -> 0
B32: 成本 （万元） | C32: 其中：1、建设费用 | D32: 维护/投入比 | E32: =H32/SUM(H18:H30) -> #DIV/0! | F32: =SUM(F33:F37) -> 0 | G32: =SUM(G33:G37) -> 16.1019 | H32: =F32+G32 -> 16.1019 | J32: =SUM(J33:J37) -> 0 | K32: =SUM(K33:K37) -> 1.1460977
C33: 1）设备采购支出 | H33: =F33+G33 -> 0 | I33: 0.13 | J33: =F33/(1+I33)*I33 -> 0 | K33: =G33/(1+I33)*I33 -> 0 | L33: 指项目建设完成后资产不归属于我公司的平台设备采购支出。
C34: 2）集成建设费用 | G34: 7.064 | H34: =F34+G34 -> 7.064 | I34: 0.06 | J34: =F34/(1+I34)*I34 -> 0 | K34: =G34/(1+I34)*I34 -> 0.39984906 | L34: 根据客户的需求，将硬件、网络、数据库及相应的应用软件进行优化整合，提供全面系统解决方案所需的项目集成建设费用。
C35: 3）中标服务费 | H35: =F35+G35 -> 0 | I35: 0.06 | J35: =F35/(1+I35)*I35 -> 0 | K35: =G35/(1+I35)*I35 -> 0 | L35: 指招标代理机构接受委托，编制招标文件(包括编制资格预审文件和标底)，审查投标人资格，组织投标人查勘现场并答疑，组织开标、评标、定标,以及提供招标前期咨询、协调合同的签订等服务所收取的费用。
C36: 4）建安费用 | G36: 9.0379 | H36: =F36+G36 -> 9.0379 | I36: 0.09 | J36: =F36/(1+I36)*I36 -> 0 | K36: =G36/(1+I36)*I36 -> 0.74624862 | L36: 指建设安装工程费。 | P36: 0.1489 | Q36: 8.889 | R36: =P36+Q36 -> 9.0379
C37: 5）其他建设费用 | H37: =F37+G37 -> 0 | J37: =F37/(1+I37)*I37 -> 0 | K37: =G37/(1+I37)*I37 -> 0 | L37: 指项目建设过程中其他费用。
C38: 2、运行维护费用 | F38: =SUM(F39:F41) -> 0 | G38: =SUM(G39:G41) -> 0 | H38: =F38+G38 -> 0 | J38: =SUM(J39:J41) -> 0 | K38: =SUM(K39:K41) -> 0
C39: 1）维护费用 | H39: =F39+G39 -> 0 | I39: 0.06 | J39: =F39/(1+I39)*I39 -> 0 | K39: =G39/(1+I39)*I39 -> 0 | L39: 指项目在运营维护过程中发生的设备维护支出及费用。
C40: 2）设备更新费用 | H40: =F40+G40 -> 0 | I40: 0.13 | J40: =F40/(1+I40)*I40 -> 0 | K40: =G40/(1+I40)*I40 -> 0 | L40: 指项目在运行过程中设备更新发生的支出及费用。
C41: 3）其他运行费用（电费、耗材等） | H41: =F41+G41 -> 0 | J41: =F41/(1+I41)*I41 -> 0 | K41: =G41/(1+I41)*I41 -> 0 | L41: 指项目在运行过程中发生的其他运行费用，如电费、耗材、场租、水费等。
C42: 3、其他直接支出 | F42: =SUM(F43:F46) -> 0 | G42: =SUM(G43:G46) -> 0 | H42: =F42+G42 -> 0 | J42: =SUM(J43:J46) -> 0 | K42: =SUM(K43:K46) -> 0
C43: 1）项目营销成本 | H43: =F43+G43 -> 0 | I43: 0.06 | J43: =F43/(1+I43)*I43 -> 0 | K43: =G43/(1+I43)*I43 -> 0 | L43: 指项目营销相关费用。
C44: 2）代理渠道酬金支出 | H44: =F44+G44 -> 0 | I44: 0.06 | J44: =F44/(1+I44)*I44 -> 0 | K44: =G44/(1+I44)*I44 -> 0 | L44: 指项目合作代理渠道的酬金支出。
C45: 3）通信业务结算支出 | H45: =F45+G45 -> 0 | I45: 0.06 | J45: =F45/(1+I45)*I45 -> 0 | K45: =G45/(1+I45)*I45 -> 0 | L45: 指项目运行过程中专线、语音、短彩信、物联网、互联网等通信业务的结算成本。
C46: 4）其他直接支出 | H46: =F46+G46 -> 0 | I46: 0.09 | J46: =F46/(1+I46)*I46 -> 0 | K46: =G46/(1+I46)*I46 -> 0 | L46: 指其他项目建设、运行和维护过程中的成本。
C47: 4、专线类项目对大网资源的分摊成本 | H47: =F47+G47 -> 0 | J47: =F47/(1+I47)*I47 -> 0 | K47: =G47/(1+I47)*I47 -> 0 | L47: ICT项目占用一定的传输资源，应考虑对上层网络资源分摊成本，分摊标准参考业务管理办法
C48: 5、集团信息化产品成本 | H48: =F48+G48 -> 0 | J48: =F48/(1+I48)*I48 -> 0 | K48: =G48/(1+I48)*I48 -> 0 | L48: 计算标准参考业务管理办法。
B49: 成本小计 | F49: =F32+F38+F42+F47+F48 -> 0 | G49: =G32+G38+G42+G47+G48 -> 16.1019 | H49: =F49+G49 -> 16.1019 | J49: =J32+J38+J42+J47+J48 -> 0 | K49: =K32+K38+K42+K47+K48 -> 1.1460977
A52: 经济效益评估
A53: 项目 年限 | B53: 1 | C53: 2 | D53: 3 | E53: 4 | F53: 5 | G53: 6 | H53: 7 | I53: 8 | J53: 9 | K53: 10 | L53: 合计 | M53: 验证
A54: 初始项目投资 | L54: =SUM(B54:K54) -> 0 | M54: =L54=-G4 -> TRUE | O54: 分类 | P54: 指标 | Q54: 评估结果 | R54: 管控要求
A55: 收入 | B55: =I4 -> 16.772251 | L55: =SUM(B55:K55) -> 16.772251 | M55: =L55=I4 -> TRUE | O55: 效益管控 | P55: 内部收益率（IRR） | Q55: =L63 -> #NUM! | R55: 13%及以上
A56: 支出 | B56: =-K4 -> -14.955802 | L56: =SUM(B56:K56) -> -14.955802 | M56: =(L56+L57)=-K4 -> TRUE | P56: 净利润率 | Q56: =L61 -> 0.081225634 | R56: 8%及以上
A57: 终端及其他营销资源投入 | L57: =SUM(B57:K57) -> 0 | O57: 底线管控 | P57: 净现值率 | Q57: =L69 -> 0.088406508 | R57: 大于0
A58: 折旧与摊销 | B58: =-折旧和摊销计算表!E2 -> 0 | C58: =-折旧和摊销计算表!F2 -> 0 | D58: =-折旧和摊销计算表!G2 -> 0 | E58: =-折旧和摊销计算表!H2 -> 0 | F58: =-折旧和摊销计算表!I2 -> 0 | G58: =-折旧和摊销计算表!J2 -> 0 | H58: =-折旧和摊销计算表!K2 -> 0 | I58: =-折旧和摊销计算表!L2 -> 0 | ... K58: =-折旧和摊销计算表!N2 -> 0 | L58: =SUM(B58:K58) -> 0 | P58: 动态回收期 | Q58: =L71 -> 0.91877437 | R58: 小于合同期，原则上不超过5年
A59: 利润总额 | B59: =B55+B56+B57+B58 -> 1.816449 | C59: =C55+C56+C57+C58 -> 0 | D59: =D55+D56+D57+D58 -> 0 | E59: =E55+E56+E57+E58 -> 0 | F59: =F55+F56+F57+F58 -> 0 | G59: =G55+G56+G57+G58 -> 0 | H59: =H55+H56+H57+H58 -> 0 | I59: =I55+I56+I57+I58 -> 0 | ... K59: =K55+K56+K57+K58 -> 0 | L59: =SUM(B59:K59) -> 1.816449
A60: 净利润（所得税率25%） | B60: =B59*(1-25%) -> 1.3623367 | C60: =C59*(1-25%) -> 0 | D60: =D59*(1-25%) -> 0 | E60: =E59*(1-25%) -> 0 | F60: =F59*(1-25%) -> 0 | G60: =G59*(1-25%) -> 0 | H60: =H59*(1-25%) -> 0 | I60: =I59*(1-25%) -> 0 | ... K60: =K59*(1-25%) -> 0 | L60: =SUM(B60:K60) -> 1.3623367
A61: 净利润率 | B61: =B60/B55 -> 0.081225634 | C61: =C60/C55 -> #DIV/0! | D61: =D60/D55 -> #DIV/0! | E61: =E60/E55 -> #DIV/0! | F61: =F60/F55 -> #DIV/0! | G61: =G60/G55 -> #DIV/0! | H61: =H60/H55 -> #DIV/0! | I61: =I60/I55 -> #DIV/0! | ... L61: =L60/L55 -> 0.081225634
A62: 折旧与摊销（加回） | B62: =-B58 -> 0 | C62: =-C58 -> 0 | D62: =-D58 -> 0 | E62: =-E58 -> 0 | F62: =-F58 -> 0 | G62: =-G58 -> 0 | H62: =-H58 -> 0 | I62: =-I58 -> 0 | ... K62: =-K58 -> 0
A63: 净现金流入（内部收益率IRR) | B63: =B60+B62+B54 -> 1.3623367 | C63: =C60+C62+C54 -> 0 | D63: =D60+D62+D54 -> 0 | E63: =E60+E62+E54 -> 0 | F63: =F60+F62+F54 -> 0 | G63: =G60+G62+G54 -> 0 | H63: =H60+H62+H54 -> 0 | I63: =I60+I62+I54 -> 0 | ... K63: =K60+K62+K54 -> 0 | L63: =IRR(B63:K63,-30%) -> #NUM!
A64: 累计净流入 | B64: =B63 -> 1.3623367 | C64: =B64+C63 -> 1.3623367 | D64: =C64+D63 -> 1.3623367 | E64: =D64+E63 -> 1.3623367 | F64: =E64+F63 -> 1.3623367 | G64: =F64+G63 -> 1.3623367 | H64: =G64+H63 -> 1.3623367 | I64: =H64+I63 -> 1.3623367 | J64: =I64+J63 -> 1.3623367 | K64: =J64+K63 -> 1.3623367
A65: 折现率（4%） | B65: =1+$A$72 -> 1.04 | C65: =B65*(1+$A$72) -> 1.0816 | D65: =C65*(1+$A$72) -> 1.124864 | E65: =D65*(1+$A$72) -> 1.1698586 | F65: =E65*(1+$A$72) -> 1.2166529 | G65: =F65*(1+$A$72) -> 1.265319 | H65: =G65*(1+$A$72) -> 1.3159318 | I65: =H65*(1+$A$72) -> 1.3685691 | J65: =I65*(1+$A$72) -> 1.4233118 | K65: =J65*(1+$A$72) -> 1.4802443
A66: 折现后现金流入 | B66: =B55/B65 -> 16.127165 | C66: =C55/C65 -> 0 | D66: =D55/D65 -> 0 | E66: =E55/E65 -> 0 | F66: =F55/F65 -> 0 | G66: =G55/G65 -> 0 | H66: =H55/H65 -> 0 | I66: =I55/I65 -> 0 | ... K66: =K55/K65 -> 0
A67: 折现后现金流出 | B67: =(B54+B56+B57-B59*0.25)/B65 -> -14.817226 | C67: =(C54+C56+C57-C59*0.25)/C65 -> 0 | D67: =(D54+D56+D57-D59*0.25)/D65 -> 0 | E67: =(E54+E56+E57-E59*0.25)/E65 -> 0 | F67: =(F54+F56+F57-F59*0.25)/F65 -> 0 | G67: =(G54+G56+G57-G59*0.25)/G65 -> 0 | H67: =(H54+H56+H57-H59*0.25)/H65 -> 0 | I67: =(I54+I56+I57-I59*0.25)/I65 -> 0 | ... K67: =(K54+K56+K57-K59*0.25)/K65 -> 0 | L67: =SUM(B67:K67) -> -14.817226
A68: 折现后净流入 | B68: =B63/B65 -> 1.3099392 | C68: =C63/C65 -> 0 | D68: =D63/D65 -> 0 | E68: =E63/E65 -> 0 | F68: =F63/F65 -> 0 | G68: =G63/G65 -> 0 | H68: =H63/H65 -> 0 | I68: =I63/I65 -> 0 | ... K68: =K63/K65 -> 0 | L68: =SUM(B68:K68) -> 1.3099392
A69: 折现后累计净流入（净现值率） | B69: =B68 -> 1.3099392 | C69: =B69+C68 -> 1.3099392 | D69: =C69+D68 -> 1.3099392 | E69: =D69+E68 -> 1.3099392 | F69: =E69+F68 -> 1.3099392 | G69: =F69+G68 -> 1.3099392 | H69: =G69+H68 -> 1.3099392 | I69: =H69+I68 -> 1.3099392 | J69: =I69+J68 -> 1.3099392 | K69: =J69+K68 -> 1.3099392 | L69: =-L68/L67 -> 0.088406508
A70: 静态回收期 | B70: =IF(B64>=0,-(B54+B56+B57-B59*0.25)/B55,"") -> 0.91877437 | C70: =IF(AND(B64<0,C64>0),B53-B64/C63,"") | D70: =IF(AND(C64<0,D64>0),C53-C64/D63,"") | E70: =IF(AND(D64<0,E64>0),D53-D64/E63,"") | F70: =IF(AND(E64<0,F64>0),E53-E64/F63,"") | G70: =IF(AND(F64<0,G64>0),F53-F64/G63,"") | H70: =IF(AND(G64<0,H64>0),G53-G64/H63,"") | L70: =LOOKUP(10,B70:K70,B70:K70) -> 0.91877437
A71: 动态回收期 | B71: =IF(B68>=0,-B67/B66,"") -> 0.91877437 | C71: =IF(AND(B69<0,C69>0),B53-B69/C68,"") | D71: =IF(AND(C69<0,D69>0),C53-C69/D68,"") | E71: =IF(AND(D69<0,E69>0),D53-D69/E68,"") | F71: =IF(AND(E69<0,F69>0),E53-E69/F68,"") | G71: =IF(AND(F69<0,G69>0),F53-F69/G68,"") | H71: =IF(AND(G69<0,H69>0),G53-G69/H68,"") | I71: =IF(AND(H69<0,I69>0),H53-H69/I68,"") | J71: =IF(AND(I69<0,J69>0),I53-I69/J68,"") | K71: =IF(AND(J69<0,K69>0),J53-J69/K68,"") | L71: =LOOKUP(10,B71:K71,B71:K71) -> 0.91877437
A72: 0.04
A75: 说明 | B75: 1、在支出方面，原则上要填写中标服务费、网络维护费用，如果没有发生此两项费用，需说明原因。 2、若项目协议期为1年且动态回收期小于1年，默认满足内部收益率管控要求，在DICT项目管理平台中按照“99”录入。 3、若出现小规模纳税人税率无法套入模板的情况，需自行在对应科目修改税率，其余情况不允许修改。

Sheet 折旧和摊销计算表
A1: 参考中国移动固定资产目录，平台类设备折旧年限为5年，传输网设备7年，光缆管道10年，软件类5年 | D1: 合计 | E1: 第一年 | F1: 第二年 | G1: 第三年 | H1: 第四年 | I1: 第五年 | J1: 第六年 | K1: 第七年 | L1: 第八年 | M1: 第九年 | N1: 第十年 | O1: 第十一年 | P1: 第十二年 | Q1: 第十三年 | R1: 第十四年 | S1: 第十五年 | T1: 第十六年 | U1: 第十七年 | V1: 第十八年 | W1: 第十九年 | X1: 第二十年
A2: 折旧及摊销 | B2: 总投资各年折旧及摊销 | D2: =SUM(E2:X2) -> 0 | E2: =E4+E20+E36+E52+E68 -> 0 | F2: =F4+F20+F36+F52+F68 -> 0 | G2: =G4+G20+G36+G52+G68 -> 0 | H2: =H4+H20+H36+H52+H68 -> 0 | I2: =I4+I20+I36+I52+I68 -> 0 | J2: =J4+J20+J36+J52+J68 -> 0 | K2: =K4+K20+K36+K52+K68 -> 0 | L2: =L4+L20+L36+L52+L68 -> 0 | ... X2: =X4+X20+X36+X52+X68 -> 0
B4: 平台类设备投资累计折旧 | D4: =SUM(E4:X4) -> 0 | E4: =SUM(E8:E18) -> 0 | F4: =SUM(F8:F18) -> 0 | G4: =SUM(G8:G18) -> 0 | H4: =SUM(H8:H18) -> 0 | I4: =SUM(I8:I18) -> 0 | J4: =SUM(J8:J18) -> 0 | K4: =SUM(K8:K18) -> 0 | L4: =SUM(L8:L18) -> 0 | ... X4: =SUM(X8:X18) -> 0
B5: 折旧年限 | C5: 5
B6: 当年投产月份 | E6: 0 | F6: 0 | G6: 0 | H6: 0 | I6: 0 | J6: 0 | K6: 0 | L6: 0 | M6: 0 | N6: 0 | O6: 0
B7: 各年平台类设备投资规模 | D7: =SUM(E7:O7) -> 0
B8: 第一年投资在各年的折旧 | D8: =SUM(E8:X8) -> 0 | E8: =F8*(1-E6/12) -> 0 | F8: =E7/C5 -> 0 | G8: =IF(SUM(E8:F8)<E7,IF((E7-SUM(E8:F8))<E7/C5,E7-SUM(E8:F8),E7/C5),0) -> 0 | H8: =IF(SUM(E8:G8)<E7,IF((E7-SUM(E8:G8))<E7/C5,E7-SUM(E8:G8),E7/C5),0) -> 0 | I8: =IF(SUM(E8:H8)<E7,IF((E7-SUM(E8:H8))<E7/C5,E7-SUM(E8:H8),E7/C5),0) -> 0 | J8: =IF(SUM(E8:I8)<E7,IF((E7-SUM(E8:I8))<E7/C5,E7-SUM(E8:I8),E7/C5),0) -> 0 | K8: =IF(SUM(E8:J8)<E7,IF((E7-SUM(E8:J8))<E7/C5,E7-SUM(E8:J8),E7/C5),0) -> 0 | L8: =IF(SUM(E8:K8)<E7,IF((E7-SUM(E8:K8))<E7/C5,E7-SUM(E8:K8),E7/C5),0) -> 0 | M8: =IF(SUM(E8:L8)<E7,IF((E7-SUM(E8:L8))<E7/C5,E7-SUM(E8:L8),E7/C5),0) -> 0 | N8: =IF(SUM(E8:M8)<E7,IF((E7-SUM(E8:M8))<E7/C5,E7-SUM(E8:M8),E7/C5),0) -> 0 | O8: =IF(SUM(E8:N8)<E7,IF((E7-SUM(E8:N8))<E7/C5,E7-SUM(E8:N8),E7/C5),0) -> 0 | P8: =IF(SUM(E8:O8)<E7,IF((E7-SUM(E8:O8))<E7/C5,E7-SUM(E8:O8),E7/C5),0) -> 0 | Q8: =IF(SUM(E8:P8)<E7,IF((E7-SUM(E8:P8))<E7/C5,E7-SUM(E8:P8),E7/C5),0) -> 0 | R8: =IF(SUM(E8:Q8)<E7,IF((E7-SUM(E8:Q8))<E7/C5,E7-SUM(E8:Q8),E7/C5),0) -> 0 | S8: =IF(SUM(E8:R8)<E7,IF((E7-SUM(E8:R8))<E7/C5,E7-SUM(E8:R8),E7/C5),0) -> 0 | T8: =IF(SUM(E8:S8)<E7,IF((E7-SUM(E8:S8))<E7/C5,E7-SUM(E8:S8),E7/C5),0) -> 0 | U8: =IF(SUM(E8:T8)<E7,IF((E7-SUM(E8:T8))<E7/C5,E7-SUM(E8:T8),E7/C5),0) -> 0 | V8: =IF(SUM(E8:U8)<E7,IF((E7-SUM(E8:U8))<E7/C5,E7-SUM(E8:U8),E7/C5),0) -> 0 | W8: =IF(SUM(E8:V8)<E7,IF((E7-SUM(E8:V8))<E7/C5,E7-SUM(E8:V8),E7/C5),0) -> 0 | X8: =IF(SUM(E8:W8)<E7,IF((E7-SUM(E8:W8))<E7/C5,E7-SUM(E8:W8),E7/C5),0) -> 0
B9: 第二年投资在各年的折旧 | D9: =SUM(E9:X9) -> 0 | F9: =G9*(1-F6/12) -> 0 | G9: =F7/C5 -> 0 | H9: =IF(SUM(E9:G9)<F7,IF((F7-SUM(E9:G9))<F7/C5,F7-SUM(E9:G9),F7/C5),0) -> 0 | I9: =IF(SUM(E9:H9)<F7,IF((F7-SUM(E9:H9))<F7/C5,F7-SUM(E9:H9),F7/C5),0) -> 0 | J9: =IF(SUM(E9:I9)<F7,IF((F7-SUM(E9:I9))<F7/C5,F7-SUM(E9:I9),F7/C5),0) -> 0 | K9: =IF(SUM(E9:J9)<F7,IF((F7-SUM(E9:J9))<F7/C5,F7-SUM(E9:J9),F7/C5),0) -> 0 | L9: =IF(SUM(E9:K9)<F7,IF((F7-SUM(E9:K9))<F7/C5,F7-SUM(E9:K9),F7/C5),0) -> 0 | M9: =IF(SUM(E9:L9)<F7,IF((F7-SUM(E9:L9))<F7/C5,F7-SUM(E9:L9),F7/C5),0) -> 0 | N9: =IF(SUM(E9:M9)<F7,IF((F7-SUM(E9:M9))<F7/C5,F7-SUM(E9:M9),F7/C5),0) -> 0 | O9: =IF(SUM(E9:N9)<F7,IF((F7-SUM(E9:N9))<F7/C5,F7-SUM(E9:N9),F7/C5),0) -> 0 | P9: =IF(SUM(E9:O9)<F7,IF((F7-SUM(E9:O9))<F7/C5,F7-SUM(E9:O9),F7/C5),0) -> 0 | Q9: =IF(SUM(E9:P9)<F7,IF((F7-SUM(E9:P9))<F7/C5,F7-SUM(E9:P9),F7/C5),0) -> 0 | R9: =IF(SUM(E9:Q9)<F7,IF((F7-SUM(E9:Q9))<F7/C5,F7-SUM(E9:Q9),F7/C5),0) -> 0 | S9: =IF(SUM(E9:R9)<F7,IF((F7-SUM(E9:R9))<F7/C5,F7-SUM(E9:R9),F7/C5),0) -> 0 | T9: =IF(SUM(E9:S9)<F7,IF((F7-SUM(E9:S9))<F7/C5,F7-SUM(E9:S9),F7/C5),0) -> 0 | U9: =IF(SUM(E9:T9)<F7,IF((F7-SUM(E9:T9))<F7/C5,F7-SUM(E9:T9),F7/C5),0) -> 0 | V9: =IF(SUM(E9:U9)<F7,IF((F7-SUM(E9:U9))<F7/C5,F7-SUM(E9:U9),F7/C5),0) -> 0 | W9: =IF(SUM(E9:V9)<F7,IF((F7-SUM(E9:V9))<F7/C5,F7-SUM(E9:V9),F7/C5),0) -> 0 | X9: =IF(SUM(E9:W9)<F7,IF((F7-SUM(E9:W9))<F7/C5,F7-SUM(E9:W9),F7/C5),0) -> 0
B10: 第三年投资在各年的折旧 | D10: =SUM(E10:X10) -> 0 | G10: =H10*(1-G6/12) -> 0 | H10: =G7/C5 -> 0 | I10: =IF(SUM(E10:H10)<G7,IF((G7-SUM(E10:H10))<G7/C5,G7-SUM(E10:H10),G7/C5),0) -> 0 | J10: =IF(SUM(E10:I10)<G7,IF((G7-SUM(E10:I10))<G7/C5,G7-SUM(E10:I10),G7/C5),0) -> 0 | K10: =IF(SUM(E10:J10)<G7,IF((G7-SUM(E10:J10))<G7/C5,G7-SUM(E10:J10),G7/C5),0) -> 0 | L10: =IF(SUM(E10:K10)<G7,IF((G7-SUM(E10:K10))<G7/C5,G7-SUM(E10:K10),G7/C5),0) -> 0 | M10: =IF(SUM(E10:L10)<G7,IF((G7-SUM(E10:L10))<G7/C5,G7-SUM(E10:L10),G7/C5),0) -> 0 | N10: =IF(SUM(E10:M10)<G7,IF((G7-SUM(E10:M10))<G7/C5,G7-SUM(E10:M10),G7/C5),0) -> 0 | O10: =IF(SUM(E10:N10)<G7,IF((G7-SUM(E10:N10))<G7/C5,G7-SUM(E10:N10),G7/C5),0) -> 0 | P10: =IF(SUM(E10:O10)<G7,IF((G7-SUM(E10:O10))<G7/C5,G7-SUM(E10:O10),G7/C5),0) -> 0 | Q10: =IF(SUM(E10:P10)<G7,IF((G7-SUM(E10:P10))<G7/C5,G7-SUM(E10:P10),G7/C5),0) -> 0 | R10: =IF(SUM(E10:Q10)<G7,IF((G7-SUM(E10:Q10))<G7/C5,G7-SUM(E10:Q10),G7/C5),0) -> 0 | S10: =IF(SUM(E10:R10)<G7,IF((G7-SUM(E10:R10))<G7/C5,G7-SUM(E10:R10),G7/C5),0) -> 0 | T10: =IF(SUM(E10:S10)<G7,IF((G7-SUM(E10:S10))<G7/C5,G7-SUM(E10:S10),G7/C5),0) -> 0 | U10: =IF(SUM(E10:T10)<G7,IF((G7-SUM(E10:T10))<G7/C5,G7-SUM(E10:T10),G7/C5),0) -> 0 | V10: =IF(SUM(E10:U10)<G7,IF((G7-SUM(E10:U10))<G7/C5,G7-SUM(E10:U10),G7/C5),0) -> 0 | W10: =IF(SUM(E10:V10)<G7,IF((G7-SUM(E10:V10))<G7/C5,G7-SUM(E10:V10),G7/C5),0) -> 0 | X10: =IF(SUM(E10:W10)<G7,IF((G7-SUM(E10:W10))<G7/C5,G7-SUM(E10:W10),G7/C5),0) -> 0
B11: 第四年投资在各年的折旧 | D11: =SUM(E11:X11) -> 0 | H11: =I11*(1-H6/12) -> 0 | I11: =H7/C5 -> 0 | J11: =IF(SUM(E11:I11)<H7,IF((H7-SUM(E11:I11))<H7/C5,H7-SUM(E11:I11),H7/C5),0) -> 0 | K11: =IF(SUM(E11:J11)<H7,IF((H7-SUM(E11:J11))<H7/C5,H7-SUM(E11:J11),H7/C5),0) -> 0 | L11: =IF(SUM(E11:K11)<H7,IF((H7-SUM(E11:K11))<H7/C5,H7-SUM(E11:K11),H7/C5),0) -> 0 | M11: =IF(SUM(E11:L11)<H7,IF((H7-SUM(E11:L11))<H7/C5,H7-SUM(E11:L11),H7/C5),0) -> 0 | N11: =IF(SUM(E11:M11)<H7,IF((H7-SUM(E11:M11))<H7/C5,H7-SUM(E11:M11),H7/C5),0) -> 0 | O11: =IF(SUM(E11:N11)<H7,IF((H7-SUM(E11:N11))<H7/C5,H7-SUM(E11:N11),H7/C5),0) -> 0 | P11: =IF(SUM(E11:O11)<H7,IF((H7-SUM(E11:O11))<H7/C5,H7-SUM(E11:O11),H7/C5),0) -> 0 | Q11: =IF(SUM(E11:P11)<H7,IF((H7-SUM(E11:P11))<H7/C5,H7-SUM(E11:P11),H7/C5),0) -> 0 | R11: =IF(SUM(E11:Q11)<H7,IF((H7-SUM(E11:Q11))<H7/C5,H7-SUM(E11:Q11),H7/C5),0) -> 0 | S11: =IF(SUM(E11:R11)<H7,IF((H7-SUM(E11:R11))<H7/C5,H7-SUM(E11:R11),H7/C5),0) -> 0 | T11: =IF(SUM(E11:S11)<H7,IF((H7-SUM(E11:S11))<H7/C5,H7-SUM(E11:S11),H7/C5),0) -> 0 | U11: =IF(SUM(E11:T11)<H7,IF((H7-SUM(E11:T11))<H7/C5,H7-SUM(E11:T11),H7/C5),0) -> 0 | V11: =IF(SUM(E11:U11)<H7,IF((H7-SUM(E11:U11))<H7/C5,H7-SUM(E11:U11),H7/C5),0) -> 0 | W11: =IF(SUM(E11:V11)<H7,IF((H7-SUM(E11:V11))<H7/C5,H7-SUM(E11:V11),H7/C5),0) -> 0 | X11: =IF(SUM(E11:W11)<H7,IF((H7-SUM(E11:W11))<H7/C5,H7-SUM(E11:W11),H7/C5),0) -> 0
B12: 第五年投资在各年的折旧 | D12: =SUM(E12:X12) -> 0 | I12: =J12*(1-I6/12) -> 0 | J12: =I7/C5 -> 0 | K12: =IF(SUM(E12:J12)<I7,IF((I7-SUM(E12:J12))<I7/C5,I7-SUM(E12:J12),I7/C5),0) -> 0 | L12: =IF(SUM(E12:K12)<I7,IF((I7-SUM(E12:K12))<I7/C5,I7-SUM(E12:K12),I7/C5),0) -> 0 | M12: =IF(SUM(E12:L12)<I7,IF((I7-SUM(E12:L12))<I7/C5,I7-SUM(E12:L12),I7/C5),0) -> 0 | N12: =IF(SUM(E12:M12)<I7,IF((I7-SUM(E12:M12))<I7/C5,I7-SUM(E12:M12),I7/C5),0) -> 0 | O12: =IF(SUM(E12:N12)<I7,IF((I7-SUM(E12:N12))<I7/C5,I7-SUM(E12:N12),I7/C5),0) -> 0 | P12: =IF(SUM(E12:O12)<I7,IF((I7-SUM(E12:O12))<I7/C5,I7-SUM(E12:O12),I7/C5),0) -> 0 | Q12: =IF(SUM(E12:P12)<I7,IF((I7-SUM(E12:P12))<I7/C5,I7-SUM(E12:P12),I7/C5),0) -> 0 | R12: =IF(SUM(E12:Q12)<I7,IF((I7-SUM(E12:Q12))<I7/C5,I7-SUM(E12:Q12),I7/C5),0) -> 0 | S12: =IF(SUM(E12:R12)<I7,IF((I7-SUM(E12:R12))<I7/C5,I7-SUM(E12:R12),I7/C5),0) -> 0 | T12: =IF(SUM(E12:S12)<I7,IF((I7-SUM(E12:S12))<I7/C5,I7-SUM(E12:S12),I7/C5),0) -> 0 | U12: =IF(SUM(E12:T12)<I7,IF((I7-SUM(E12:T12))<I7/C5,I7-SUM(E12:T12),I7/C5),0) -> 0 | V12: =IF(SUM(E12:U12)<I7,IF((I7-SUM(E12:U12))<I7/C5,I7-SUM(E12:U12),I7/C5),0) -> 0 | W12: =IF(SUM(E12:V12)<I7,IF((I7-SUM(E12:V12))<I7/C5,I7-SUM(E12:V12),I7/C5),0) -> 0 | X12: =IF(SUM(E12:W12)<I7,IF((I7-SUM(E12:W12))<I7/C5,I7-SUM(E12:W12),I7/C5),0) -> 0
B13: 第六年投资在各年的折旧 | D13: =SUM(E13:X13) -> 0 | J13: =K13*(1-J6/12) -> 0 | K13: =J7/C5 -> 0 | L13: =IF(SUM(E13:K13)<J7,IF((J7-SUM(E13:K13))<J7/C5,J7-SUM(E13:K13),J7/C5),0) -> 0 | M13: =IF(SUM(E13:L13)<J7,IF((J7-SUM(E13:L13))<J7/C5,J7-SUM(E13:L13),J7/C5),0) -> 0 | N13: =IF(SUM(E13:M13)<J7,IF((J7-SUM(E13:M13))<J7/C5,J7-SUM(E13:M13),J7/C5),0) -> 0 | O13: =IF(SUM(E13:N13)<J7,IF((J7-SUM(E13:N13))<J7/C5,J7-SUM(E13:N13),J7/C5),0) -> 0 | P13: =IF(SUM(E13:O13)<J7,IF((J7-SUM(E13:O13))<J7/C5,J7-SUM(E13:O13),J7/C5),0) -> 0 | Q13: =IF(SUM(E13:P13)<J7,IF((J7-SUM(E13:P13))<J7/C5,J7-SUM(E13:P13),J7/C5),0) -> 0 | R13: =IF(SUM(E13:Q13)<J7,IF((J7-SUM(E13:Q13))<J7/C5,J7-SUM(E13:Q13),J7/C5),0) -> 0 | S13: =IF(SUM(E13:R13)<J7,IF((J7-SUM(E13:R13))<J7/C5,J7-SUM(E13:R13),J7/C5),0) -> 0 | T13: =IF(SUM(E13:S13)<J7,IF((J7-SUM(E13:S13))<J7/C5,J7-SUM(E13:S13),J7/C5),0) -> 0 | U13: =IF(SUM(E13:T13)<J7,IF((J7-SUM(E13:T13))<J7/C5,J7-SUM(E13:T13),J7/C5),0) -> 0 | V13: =IF(SUM(E13:U13)<J7,IF((J7-SUM(E13:U13))<J7/C5,J7-SUM(E13:U13),J7/C5),0) -> 0 | W13: =IF(SUM(E13:V13)<J7,IF((J7-SUM(E13:V13))<J7/C5,J7-SUM(E13:V13),J7/C5),0) -> 0 | X13: =IF(SUM(E13:W13)<J7,IF((J7-SUM(E13:W13))<J7/C5,J7-SUM(E13:W13),J7/C5),0) -> 0
B14: 第七年投资在各年的折旧 | D14: =SUM(E14:X14) -> 0 | K14: =L14*(1-K6/12) -> 0 | L14: =K7/C5 -> 0 | M14: =IF(SUM(E14:L14)<K7,IF((K7-SUM(E14:L14))<K7/C5,K7-SUM(E14:L14),K7/C5),0) -> 0 | N14: =IF(SUM(E14:M14)<K7,IF((K7-SUM(E14:M14))<K7/C5,K7-SUM(E14:M14),K7/C5),0) -> 0 | O14: =IF(SUM(E14:N14)<K7,IF((K7-SUM(E14:N14))<K7/C5,K7-SUM(E14:N14),K7/C5),0) -> 0 | P14: =IF(SUM(E14:O14)<K7,IF((K7-SUM(E14:O14))<K7/C5,K7-SUM(E14:O14),K7/C5),0) -> 0 | Q14: =IF(SUM(E14:P14)<K7,IF((K7-SUM(E14:P14))<K7/C5,K7-SUM(E14:P14),K7/C5),0) -> 0 | R14: =IF(SUM(E14:Q14)<K7,IF((K7-SUM(E14:Q14))<K7/C5,K7-SUM(E14:Q14),K7/C5),0) -> 0 | S14: =IF(SUM(E14:R14)<K7,IF((K7-SUM(E14:R14))<K7/C5,K7-SUM(E14:R14),K7/C5),0) -> 0 | T14: =IF(SUM(E14:S14)<K7,IF((K7-SUM(E14:S14))<K7/C5,K7-SUM(E14:S14),K7/C5),0) -> 0 | U14: =IF(SUM(E14:T14)<K7,IF((K7-SUM(E14:T14))<K7/C5,K7-SUM(E14:T14),K7/C5),0) -> 0 | V14: =IF(SUM(E14:U14)<K7,IF((K7-SUM(E14:U14))<K7/C5,K7-SUM(E14:U14),K7/C5),0) -> 0 | W14: =IF(SUM(E14:V14)<K7,IF((K7-SUM(E14:V14))<K7/C5,K7-SUM(E14:V14),K7/C5),0) -> 0 | X14: =IF(SUM(E14:W14)<K7,IF((K7-SUM(E14:W14))<K7/C5,K7-SUM(E14:W14),K7/C5),0) -> 0
B15: 第八年投资在各年的折旧 | D15: =SUM(E15:X15) -> 0 | L15: =M15*(1-L6/12) -> 0 | M15: =L7/C5 -> 0 | N15: =IF(SUM(E15:M15)<L7,IF((L7-SUM(E15:M15))<L7/C5,L7-SUM(E15:M15),L7/C5),0) -> 0 | O15: =IF(SUM(E15:N15)<L7,IF((L7-SUM(E15:N15))<L7/C5,L7-SUM(E15:N15),L7/C5),0) -> 0 | P15: =IF(SUM(E15:O15)<L7,IF((L7-SUM(E15:O15))<L7/C5,L7-SUM(E15:O15),L7/C5),0) -> 0 | Q15: =IF(SUM(E15:P15)<L7,IF((L7-SUM(E15:P15))<L7/C5,L7-SUM(E15:P15),L7/C5),0) -> 0 | R15: =IF(SUM(E15:Q15)<L7,IF((L7-SUM(E15:Q15))<L7/C5,L7-SUM(E15:Q15),L7/C5),0) -> 0 | S15: =IF(SUM(E15:R15)<L7,IF((L7-SUM(E15:R15))<L7/C5,L7-SUM(E15:R15),L7/C5),0) -> 0 | T15: =IF(SUM(E15:S15)<L7,IF((L7-SUM(E15:S15))<L7/C5,L7-SUM(E15:S15),L7/C5),0) -> 0 | U15: =IF(SUM(E15:T15)<L7,IF((L7-SUM(E15:T15))<L7/C5,L7-SUM(E15:T15),L7/C5),0) -> 0 | V15: =IF(SUM(E15:U15)<L7,IF((L7-SUM(E15:U15))<L7/C5,L7-SUM(E15:U15),L7/C5),0) -> 0 | W15: =IF(SUM(E15:V15)<L7,IF((L7-SUM(E15:V15))<L7/C5,L7-SUM(E15:V15),L7/C5),0) -> 0 | X15: =IF(SUM(E15:W15)<L7,IF((L7-SUM(E15:W15))<L7/C5,L7-SUM(E15:W15),L7/C5),0) -> 0
B16: 第九年投资在各年的折旧 | D16: =SUM(E16:X16) -> 0 | M16: =N16*(1-M6/12) -> 0 | N16: =M7/C5 -> 0 | O16: =IF(SUM(E16:N16)<M7,IF((M7-SUM(E16:N16))<M7/C5,M7-SUM(E16:N16),M7/C5),0) -> 0 | P16: =IF(SUM(E16:O16)<M7,IF((M7-SUM(E16:O16))<M7/C5,M7-SUM(E16:O16),M7/C5),0) -> 0 | Q16: =IF(SUM(E16:P16)<M7,IF((M7-SUM(E16:P16))<M7/C5,M7-SUM(E16:P16),M7/C5),0) -> 0 | R16: =IF(SUM(E16:Q16)<M7,IF((M7-SUM(E16:Q16))<M7/C5,M7-SUM(E16:Q16),M7/C5),0) -> 0 | S16: =IF(SUM(E16:R16)<M7,IF((M7-SUM(E16:R16))<M7/C5,M7-SUM(E16:R16),M7/C5),0) -> 0 | T16: =IF(SUM(E16:S16)<M7,IF((M7-SUM(E16:S16))<M7/C5,M7-SUM(E16:S16),M7/C5),0) -> 0 | U16: =IF(SUM(E16:T16)<M7,IF((M7-SUM(E16:T16))<M7/C5,M7-SUM(E16:T16),M7/C5),0) -> 0 | V16: =IF(SUM(E16:U16)<M7,IF((M7-SUM(E16:U16))<M7/C5,M7-SUM(E16:U16),M7/C5),0) -> 0 | W16: =IF(SUM(E16:V16)<M7,IF((M7-SUM(E16:V16))<M7/C5,M7-SUM(E16:V16),M7/C5),0) -> 0 | X16: =IF(SUM(E16:W16)<M7,IF((M7-SUM(E16:W16))<M7/C5,M7-SUM(E16:W16),M7/C5),0) -> 0
B17: 第十年投资在各年的折旧 | D17: =SUM(E17:X17) -> 0 | N17: =O17*(1-N6/12) -> 0 | O17: =N7/C5 -> 0 | P17: =IF(SUM(E17:O17)<N7,IF((N7-SUM(E17:O17))<N7/C5,N7-SUM(E17:O17),N7/C5),0) -> 0 | Q17: =IF(SUM(E17:P17)<N7,IF((N7-SUM(E17:P17))<N7/C5,N7-SUM(E17:P17),N7/C5),0) -> 0 | R17: =IF(SUM(E17:Q17)<N7,IF((N7-SUM(E17:Q17))<N7/C5,N7-SUM(E17:Q17),N7/C5),0) -> 0 | S17: =IF(SUM(E17:R17)<N7,IF((N7-SUM(E17:R17))<N7/C5,N7-SUM(E17:R17),N7/C5),0) -> 0 | T17: =IF(SUM(E17:S17)<N7,IF((N7-SUM(E17:S17))<N7/C5,N7-SUM(E17:S17),N7/C5),0) -> 0 | U17: =IF(SUM(E17:T17)<N7,IF((N7-SUM(E17:T17))<N7/C5,N7-SUM(E17:T17),N7/C5),0) -> 0 | V17: =IF(SUM(E17:U17)<N7,IF((N7-SUM(E17:U17))<N7/C5,N7-SUM(E17:U17),N7/C5),0) -> 0 | W17: =IF(SUM(E17:V17)<N7,IF((N7-SUM(E17:V17))<N7/C5,N7-SUM(E17:V17),N7/C5),0) -> 0 | X17: =IF(SUM(E17:W17)<N7,IF((N7-SUM(E17:W17))<N7/C5,N7-SUM(E17:W17),N7/C5),0) -> 0
B18: 第十一年投资在各年的折旧 | D18: =SUM(E18:X18) -> 0 | O18: =P18*(1-O6/12) -> 0 | P18: =O7/C5 -> 0 | Q18: =IF(SUM(E18:P18)<O7,IF((O7-SUM(E18:P18))<O7/C5,O7-SUM(E18:P18),O7/C5),0) -> 0 | R18: =IF(SUM(E18:Q18)<O7,IF((O7-SUM(E18:Q18))<O7/C5,O7-SUM(E18:Q18),O7/C5),0) -> 0 | S18: =IF(SUM(E18:R18)<O7,IF((O7-SUM(E18:R18))<O7/C5,O7-SUM(E18:R18),O7/C5),0) -> 0 | T18: =IF(SUM(E18:S18)<O7,IF((O7-SUM(E18:S18))<O7/C5,O7-SUM(E18:S18),O7/C5),0) -> 0 | U18: =IF(SUM(E18:T18)<O7,IF((O7-SUM(E18:T18))<O7/C5,O7-SUM(E18:T18),O7/C5),0) -> 0 | V18: =IF(SUM(E18:U18)<O7,IF((O7-SUM(E18:U18))<O7/C5,O7-SUM(E18:U18),O7/C5),0) -> 0 | W18: =IF(SUM(E18:V18)<O7,IF((O7-SUM(E18:V18))<O7/C5,O7-SUM(E18:V18),O7/C5),0) -> 0 | X18: =IF(SUM(E18:W18)<O7,IF((O7-SUM(E18:W18))<O7/C5,O7-SUM(E18:W18),O7/C5),0) -> 0
B20: 传输网设备类投资累计折旧 | D20: =SUM(E20:X20) -> 0 | E20: =SUM(E24:E34) -> 0 | F20: =SUM(F24:F34) -> 0 | G20: =SUM(G24:G34) -> 0 | H20: =SUM(H24:H34) -> 0 | I20: =SUM(I24:I34) -> 0 | J20: =SUM(J24:J34) -> 0 | K20: =SUM(K24:K34) -> 0 | L20: =SUM(L24:L34) -> 0 | ... X20: =SUM(X24:X34) -> 0
B21: 折旧年限 | C21: 7
B22: 当年投产月份 | E22: 0 | F22: 0 | G22: 0 | H22: 6 | I22: 0 | J22: 0 | K22: 0 | L22: 0 | M22: 0 | N22: 0 | O22: 0
B23: 各年传输网设备类投资规模 | D23: =SUM(E23:O23) -> 0
B24: 第一年投资在各年的折旧 | D24: =SUM(E24:X24) -> 0 | E24: =F24*(1-E22/12) -> 0 | F24: =E23/C21 -> 0 | G24: =IF(SUM(E24:F24)<E23,IF((E23-SUM(E24:F24))<E23/C21,E23-SUM(E24:F24),E23/C21),0) -> 0 | H24: =IF(SUM(E24:G24)<E23,IF((E23-SUM(E24:G24))<E23/C21,E23-SUM(E24:G24),E23/C21),0) -> 0 | I24: =IF(SUM(E24:H24)<E23,IF((E23-SUM(E24:H24))<E23/C21,E23-SUM(E24:H24),E23/C21),0) -> 0 | J24: =IF(SUM(E24:I24)<E23,IF((E23-SUM(E24:I24))<E23/C21,E23-SUM(E24:I24),E23/C21),0) -> 0 | K24: =IF(SUM(E24:J24)<E23,IF((E23-SUM(E24:J24))<E23/C21,E23-SUM(E24:J24),E23/C21),0) -> 0 | L24: =IF(SUM(E24:K24)<E23,IF((E23-SUM(E24:K24))<E23/C21,E23-SUM(E24:K24),E23/C21),0) -> 0 | M24: =IF(SUM(E24:L24)<E23,IF((E23-SUM(E24:L24))<E23/C21,E23-SUM(E24:L24),E23/C21),0) -> 0 | N24: =IF(SUM(E24:M24)<E23,IF((E23-SUM(E24:M24))<E23/C21,E23-SUM(E24:M24),E23/C21),0) -> 0 | O24: =IF(SUM(E24:N24)<E23,IF((E23-SUM(E24:N24))<E23/C21,E23-SUM(E24:N24),E23/C21),0) -> 0 | P24: =IF(SUM(E24:O24)<E23,IF((E23-SUM(E24:O24))<E23/C21,E23-SUM(E24:O24),E23/C21),0) -> 0 | Q24: =IF(SUM(E24:P24)<E23,IF((E23-SUM(E24:P24))<E23/C21,E23-SUM(E24:P24),E23/C21),0) -> 0 | R24: =IF(SUM(E24:Q24)<E23,IF((E23-SUM(E24:Q24))<E23/C21,E23-SUM(E24:Q24),E23/C21),0) -> 0 | S24: =IF(SUM(E24:R24)<E23,IF((E23-SUM(E24:R24))<E23/C21,E23-SUM(E24:R24),E23/C21),0) -> 0 | T24: =IF(SUM(E24:S24)<E23,IF((E23-SUM(E24:S24))<E23/C21,E23-SUM(E24:S24),E23/C21),0) -> 0 | U24: =IF(SUM(E24:T24)<E23,IF((E23-SUM(E24:T24))<E23/C21,E23-SUM(E24:T24),E23/C21),0) -> 0 | V24: =IF(SUM(E24:U24)<E23,IF((E23-SUM(E24:U24))<E23/C21,E23-SUM(E24:U24),E23/C21),0) -> 0 | W24: =IF(SUM(E24:V24)<E23,IF((E23-SUM(E24:V24))<E23/C21,E23-SUM(E24:V24),E23/C21),0) -> 0 | X24: =IF(SUM(E24:W24)<E23,IF((E23-SUM(E24:W24))<E23/C21,E23-SUM(E24:W24),E23/C21),0) -> 0
B25: 第二年投资在各年的折旧 | D25: =SUM(E25:X25) -> 0 | F25: =G25*(1-F22/12) -> 0 | G25: =F23/C21 -> 0 | H25: =IF(SUM(E25:G25)<F23,IF((F23-SUM(E25:G25))<F23/C21,F23-SUM(E25:G25),F23/C21),0) -> 0 | I25: =IF(SUM(E25:H25)<F23,IF((F23-SUM(E25:H25))<F23/C21,F23-SUM(E25:H25),F23/C21),0) -> 0 | J25: =IF(SUM(E25:I25)<F23,IF((F23-SUM(E25:I25))<F23/C21,F23-SUM(E25:I25),F23/C21),0) -> 0 | K25: =IF(SUM(E25:J25)<F23,IF((F23-SUM(E25:J25))<F23/C21,F23-SUM(E25:J25),F23/C21),0) -> 0 | L25: =IF(SUM(E25:K25)<F23,IF((F23-SUM(E25:K25))<F23/C21,F23-SUM(E25:K25),F23/C21),0) -> 0 | M25: =IF(SUM(E25:L25)<F23,IF((F23-SUM(E25:L25))<F23/C21,F23-SUM(E25:L25),F23/C21),0) -> 0 | N25: =IF(SUM(E25:M25)<F23,IF((F23-SUM(E25:M25))<F23/C21,F23-SUM(E25:M25),F23/C21),0) -> 0 | O25: =IF(SUM(E25:N25)<F23,IF((F23-SUM(E25:N25))<F23/C21,F23-SUM(E25:N25),F23/C21),0) -> 0 | P25: =IF(SUM(E25:O25)<F23,IF((F23-SUM(E25:O25))<F23/C21,F23-SUM(E25:O25),F23/C21),0) -> 0 | Q25: =IF(SUM(E25:P25)<F23,IF((F23-SUM(E25:P25))<F23/C21,F23-SUM(E25:P25),F23/C21),0) -> 0 | R25: =IF(SUM(E25:Q25)<F23,IF((F23-SUM(E25:Q25))<F23/C21,F23-SUM(E25:Q25),F23/C21),0) -> 0 | S25: =IF(SUM(E25:R25)<F23,IF((F23-SUM(E25:R25))<F23/C21,F23-SUM(E25:R25),F23/C21),0) -> 0 | T25: =IF(SUM(E25:S25)<F23,IF((F23-SUM(E25:S25))<F23/C21,F23-SUM(E25:S25),F23/C21),0) -> 0 | U25: =IF(SUM(E25:T25)<F23,IF((F23-SUM(E25:T25))<F23/C21,F23-SUM(E25:T25),F23/C21),0) -> 0 | V25: =IF(SUM(E25:U25)<F23,IF((F23-SUM(E25:U25))<F23/C21,F23-SUM(E25:U25),F23/C21),0) -> 0 | W25: =IF(SUM(E25:V25)<F23,IF((F23-SUM(E25:V25))<F23/C21,F23-SUM(E25:V25),F23/C21),0) -> 0 | X25: =IF(SUM(E25:W25)<F23,IF((F23-SUM(E25:W25))<F23/C21,F23-SUM(E25:W25),F23/C21),0) -> 0
B26: 第三年投资在各年的折旧 | D26: =SUM(E26:X26) -> 0 | G26: =H26*(1-G22/12) -> 0 | H26: =G23/C21 -> 0 | I26: =IF(SUM(E26:H26)<G23,IF((G23-SUM(E26:H26))<G23/C21,G23-SUM(E26:H26),G23/C21),0) -> 0 | J26: =IF(SUM(E26:I26)<G23,IF((G23-SUM(E26:I26))<G23/C21,G23-SUM(E26:I26),G23/C21),0) -> 0 | K26: =IF(SUM(E26:J26)<G23,IF((G23-SUM(E26:J26))<G23/C21,G23-SUM(E26:J26),G23/C21),0) -> 0 | L26: =IF(SUM(E26:K26)<G23,IF((G23-SUM(E26:K26))<G23/C21,G23-SUM(E26:K26),G23/C21),0) -> 0 | M26: =IF(SUM(E26:L26)<G23,IF((G23-SUM(E26:L26))<G23/C21,G23-SUM(E26:L26),G23/C21),0) -> 0 | N26: =IF(SUM(E26:M26)<G23,IF((G23-SUM(E26:M26))<G23/C21,G23-SUM(E26:M26),G23/C21),0) -> 0 | O26: =IF(SUM(E26:N26)<G23,IF((G23-SUM(E26:N26))<G23/C21,G23-SUM(E26:N26),G23/C21),0) -> 0 | P26: =IF(SUM(E26:O26)<G23,IF((G23-SUM(E26:O26))<G23/C21,G23-SUM(E26:O26),G23/C21),0) -> 0 | Q26: =IF(SUM(E26:P26)<G23,IF((G23-SUM(E26:P26))<G23/C21,G23-SUM(E26:P26),G23/C21),0) -> 0 | R26: =IF(SUM(E26:Q26)<G23,IF((G23-SUM(E26:Q26))<G23/C21,G23-SUM(E26:Q26),G23/C21),0) -> 0 | S26: =IF(SUM(E26:R26)<G23,IF((G23-SUM(E26:R26))<G23/C21,G23-SUM(E26:R26),G23/C21),0) -> 0 | T26: =IF(SUM(E26:S26)<G23,IF((G23-SUM(E26:S26))<G23/C21,G23-SUM(E26:S26),G23/C21),0) -> 0 | U26: =IF(SUM(E26:T26)<G23,IF((G23-SUM(E26:T26))<G23/C21,G23-SUM(E26:T26),G23/C21),0) -> 0 | V26: =IF(SUM(E26:U26)<G23,IF((G23-SUM(E26:U26))<G23/C21,G23-SUM(E26:U26),G23/C21),0) -> 0 | W26: =IF(SUM(E26:V26)<G23,IF((G23-SUM(E26:V26))<G23/C21,G23-SUM(E26:V26),G23/C21),0) -> 0 | X26: =IF(SUM(E26:W26)<G23,IF((G23-SUM(E26:W26))<G23/C21,G23-SUM(E26:W26),G23/C21),0) -> 0
B27: 第四年投资在各年的折旧 | D27: =SUM(E27:X27) -> 0 | H27: =I27*(1-H22/12) -> 0 | I27: =H23/C21 -> 0 | J27: =IF(SUM(E27:I27)<H23,IF((H23-SUM(E27:I27))<H23/C21,H23-SUM(E27:I27),H23/C21),0) -> 0 | K27: =IF(SUM(E27:J27)<H23,IF((H23-SUM(E27:J27))<H23/C21,H23-SUM(E27:J27),H23/C21),0) -> 0 | L27: =IF(SUM(E27:K27)<H23,IF((H23-SUM(E27:K27))<H23/C21,H23-SUM(E27:K27),H23/C21),0) -> 0 | M27: =IF(SUM(E27:L27)<H23,IF((H23-SUM(E27:L27))<H23/C21,H23-SUM(E27:L27),H23/C21),0) -> 0 | N27: =IF(SUM(E27:M27)<H23,IF((H23-SUM(E27:M27))<H23/C21,H23-SUM(E27:M27),H23/C21),0) -> 0 | O27: =IF(SUM(E27:N27)<H23,IF((H23-SUM(E27:N27))<H23/C21,H23-SUM(E27:N27),H23/C21),0) -> 0 | P27: =IF(SUM(E27:O27)<H23,IF((H23-SUM(E27:O27))<H23/C21,H23-SUM(E27:O27),H23/C21),0) -> 0 | Q27: =IF(SUM(E27:P27)<H23,IF((H23-SUM(E27:P27))<H23/C21,H23-SUM(E27:P27),H23/C21),0) -> 0 | R27: =IF(SUM(E27:Q27)<H23,IF((H23-SUM(E27:Q27))<H23/C21,H23-SUM(E27:Q27),H23/C21),0) -> 0 | S27: =IF(SUM(E27:R27)<H23,IF((H23-SUM(E27:R27))<H23/C21,H23-SUM(E27:R27),H23/C21),0) -> 0 | T27: =IF(SUM(E27:S27)<H23,IF((H23-SUM(E27:S27))<H23/C21,H23-SUM(E27:S27),H23/C21),0) -> 0 | U27: =IF(SUM(E27:T27)<H23,IF((H23-SUM(E27:T27))<H23/C21,H23-SUM(E27:T27),H23/C21),0) -> 0 | V27: =IF(SUM(E27:U27)<H23,IF((H23-SUM(E27:U27))<H23/C21,H23-SUM(E27:U27),H23/C21),0) -> 0 | W27: =IF(SUM(E27:V27)<H23,IF((H23-SUM(E27:V27))<H23/C21,H23-SUM(E27:V27),H23/C21),0) -> 0 | X27: =IF(SUM(E27:W27)<H23,IF((H23-SUM(E27:W27))<H23/C21,H23-SUM(E27:W27),H23/C21),0) -> 0
B28: 第五年投资在各年的折旧 | D28: =SUM(E28:X28) -> 0 | I28: =J28*(1-I22/12) -> 0 | J28: =I23/C21 -> 0 | K28: =IF(SUM(E28:J28)<I23,IF((I23-SUM(E28:J28))<I23/C21,I23-SUM(E28:J28),I23/C21),0) -> 0 | L28: =IF(SUM(E28:K28)<I23,IF((I23-SUM(E28:K28))<I23/C21,I23-SUM(E28:K28),I23/C21),0) -> 0 | M28: =IF(SUM(E28:L28)<I23,IF((I23-SUM(E28:L28))<I23/C21,I23-SUM(E28:L28),I23/C21),0) -> 0 | N28: =IF(SUM(E28:M28)<I23,IF((I23-SUM(E28:M28))<I23/C21,I23-SUM(E28:M28),I23/C21),0) -> 0 | O28: =IF(SUM(E28:N28)<I23,IF((I23-SUM(E28:N28))<I23/C21,I23-SUM(E28:N28),I23/C21),0) -> 0 | P28: =IF(SUM(E28:O28)<I23,IF((I23-SUM(E28:O28))<I23/C21,I23-SUM(E28:O28),I23/C21),0) -> 0 | Q28: =IF(SUM(E28:P28)<I23,IF((I23-SUM(E28:P28))<I23/C21,I23-SUM(E28:P28),I23/C21),0) -> 0 | R28: =IF(SUM(E28:Q28)<I23,IF((I23-SUM(E28:Q28))<I23/C21,I23-SUM(E28:Q28),I23/C21),0) -> 0 | S28: =IF(SUM(E28:R28)<I23,IF((I23-SUM(E28:R28))<I23/C21,I23-SUM(E28:R28),I23/C21),0) -> 0 | T28: =IF(SUM(E28:S28)<I23,IF((I23-SUM(E28:S28))<I23/C21,I23-SUM(E28:S28),I23/C21),0) -> 0 | U28: =IF(SUM(E28:T28)<I23,IF((I23-SUM(E28:T28))<I23/C21,I23-SUM(E28:T28),I23/C21),0) -> 0 | V28: =IF(SUM(E28:U28)<I23,IF((I23-SUM(E28:U28))<I23/C21,I23-SUM(E28:U28),I23/C21),0) -> 0 | W28: =IF(SUM(E28:V28)<I23,IF((I23-SUM(E28:V28))<I23/C21,I23-SUM(E28:V28),I23/C21),0) -> 0 | X28: =IF(SUM(E28:W28)<I23,IF((I23-SUM(E28:W28))<I23/C21,I23-SUM(E28:W28),I23/C21),0) -> 0
B29: 第六年投资在各年的折旧 | D29: =SUM(E29:X29) -> 0 | J29: =K29*(1-J22/12) -> 0 | K29: =J23/C21 -> 0 | L29: =IF(SUM(E29:K29)<J23,IF((J23-SUM(E29:K29))<J23/C21,J23-SUM(E29:K29),J23/C21),0) -> 0 | M29: =IF(SUM(E29:L29)<J23,IF((J23-SUM(E29:L29))<J23/C21,J23-SUM(E29:L29),J23/C21),0) -> 0 | N29: =IF(SUM(E29:M29)<J23,IF((J23-SUM(E29:M29))<J23/C21,J23-SUM(E29:M29),J23/C21),0) -> 0 | O29: =IF(SUM(E29:N29)<J23,IF((J23-SUM(E29:N29))<J23/C21,J23-SUM(E29:N29),J23/C21),0) -> 0 | P29: =IF(SUM(E29:O29)<J23,IF((J23-SUM(E29:O29))<J23/C21,J23-SUM(E29:O29),J23/C21),0) -> 0 | Q29: =IF(SUM(E29:P29)<J23,IF((J23-SUM(E29:P29))<J23/C21,J23-SUM(E29:P29),J23/C21),0) -> 0 | R29: =IF(SUM(E29:Q29)<J23,IF((J23-SUM(E29:Q29))<J23/C21,J23-SUM(E29:Q29),J23/C21),0) -> 0 | S29: =IF(SUM(E29:R29)<J23,IF((J23-SUM(E29:R29))<J23/C21,J23-SUM(E29:R29),J23/C21),0) -> 0 | T29: =IF(SUM(E29:S29)<J23,IF((J23-SUM(E29:S29))<J23/C21,J23-SUM(E29:S29),J23/C21),0) -> 0 | U29: =IF(SUM(E29:T29)<J23,IF((J23-SUM(E29:T29))<J23/C21,J23-SUM(E29:T29),J23/C21),0) -> 0 | V29: =IF(SUM(E29:U29)<J23,IF((J23-SUM(E29:U29))<J23/C21,J23-SUM(E29:U29),J23/C21),0) -> 0 | W29: =IF(SUM(E29:V29)<J23,IF((J23-SUM(E29:V29))<J23/C21,J23-SUM(E29:V29),J23/C21),0) -> 0 | X29: =IF(SUM(E29:W29)<J23,IF((J23-SUM(E29:W29))<J23/C21,J23-SUM(E29:W29),J23/C21),0) -> 0
B30: 第七年投资在各年的折旧 | D30: =SUM(E30:X30) -> 0 | K30: =L30*(1-K22/12) -> 0 | L30: =K23/C21 -> 0 | M30: =IF(SUM(E30:L30)<K23,IF((K23-SUM(E30:L30))<K23/C21,K23-SUM(E30:L30),K23/C21),0) -> 0 | N30: =IF(SUM(E30:M30)<K23,IF((K23-SUM(E30:M30))<K23/C21,K23-SUM(E30:M30),K23/C21),0) -> 0 | O30: =IF(SUM(E30:N30)<K23,IF((K23-SUM(E30:N30))<K23/C21,K23-SUM(E30:N30),K23/C21),0) -> 0 | P30: =IF(SUM(E30:O30)<K23,IF((K23-SUM(E30:O30))<K23/C21,K23-SUM(E30:O30),K23/C21),0) -> 0 | Q30: =IF(SUM(E30:P30)<K23,IF((K23-SUM(E30:P30))<K23/C21,K23-SUM(E30:P30),K23/C21),0) -> 0 | R30: =IF(SUM(E30:Q30)<K23,IF((K23-SUM(E30:Q30))<K23/C21,K23-SUM(E30:Q30),K23/C21),0) -> 0 | S30: =IF(SUM(E30:R30)<K23,IF((K23-SUM(E30:R30))<K23/C21,K23-SUM(E30:R30),K23/C21),0) -> 0 | T30: =IF(SUM(E30:S30)<K23,IF((K23-SUM(E30:S30))<K23/C21,K23-SUM(E30:S30),K23/C21),0) -> 0 | U30: =IF(SUM(E30:T30)<K23,IF((K23-SUM(E30:T30))<K23/C21,K23-SUM(E30:T30),K23/C21),0) -> 0 | V30: =IF(SUM(E30:U30)<K23,IF((K23-SUM(E30:U30))<K23/C21,K23-SUM(E30:U30),K23/C21),0) -> 0 | W30: =IF(SUM(E30:V30)<K23,IF((K23-SUM(E30:V30))<K23/C21,K23-SUM(E30:V30),K23/C21),0) -> 0 | X30: =IF(SUM(E30:W30)<K23,IF((K23-SUM(E30:W30))<K23/C21,K23-SUM(E30:W30),K23/C21),0) -> 0
B31: 第八年投资在各年的折旧 | D31: =SUM(E31:X31) -> 0 | L31: =M31*(1-L22/12) -> 0 | M31: =L23/C21 -> 0 | N31: =IF(SUM(E31:M31)<L23,IF((L23-SUM(E31:M31))<L23/C21,L23-SUM(E31:M31),L23/C21),0) -> 0 | O31: =IF(SUM(E31:N31)<L23,IF((L23-SUM(E31:N31))<L23/C21,L23-SUM(E31:N31),L23/C21),0) -> 0 | P31: =IF(SUM(E31:O31)<L23,IF((L23-SUM(E31:O31))<L23/C21,L23-SUM(E31:O31),L23/C21),0) -> 0 | Q31: =IF(SUM(E31:P31)<L23,IF((L23-SUM(E31:P31))<L23/C21,L23-SUM(E31:P31),L23/C21),0) -> 0 | R31: =IF(SUM(E31:Q31)<L23,IF((L23-SUM(E31:Q31))<L23/C21,L23-SUM(E31:Q31),L23/C21),0) -> 0 | S31: =IF(SUM(E31:R31)<L23,IF((L23-SUM(E31:R31))<L23/C21,L23-SUM(E31:R31),L23/C21),0) -> 0 | T31: =IF(SUM(E31:S31)<L23,IF((L23-SUM(E31:S31))<L23/C21,L23-SUM(E31:S31),L23/C21),0) -> 0 | U31: =IF(SUM(E31:T31)<L23,IF((L23-SUM(E31:T31))<L23/C21,L23-SUM(E31:T31),L23/C21),0) -> 0 | V31: =IF(SUM(E31:U31)<L23,IF((L23-SUM(E31:U31))<L23/C21,L23-SUM(E31:U31),L23/C21),0) -> 0 | W31: =IF(SUM(E31:V31)<L23,IF((L23-SUM(E31:V31))<L23/C21,L23-SUM(E31:V31),L23/C21),0) -> 0 | X31: =IF(SUM(E31:W31)<L23,IF((L23-SUM(E31:W31))<L23/C21,L23-SUM(E31:W31),L23/C21),0) -> 0
B32: 第九年投资在各年的折旧 | D32: =SUM(E32:X32) -> 0 | M32: =N32*(1-M22/12) -> 0 | N32: =M23/C21 -> 0 | O32: =IF(SUM(E32:N32)<M23,IF((M23-SUM(E32:N32))<M23/C21,M23-SUM(E32:N32),M23/C21),0) -> 0 | P32: =IF(SUM(E32:O32)<M23,IF((M23-SUM(E32:O32))<M23/C21,M23-SUM(E32:O32),M23/C21),0) -> 0 | Q32: =IF(SUM(E32:P32)<M23,IF((M23-SUM(E32:P32))<M23/C21,M23-SUM(E32:P32),M23/C21),0) -> 0 | R32: =IF(SUM(E32:Q32)<M23,IF((M23-SUM(E32:Q32))<M23/C21,M23-SUM(E32:Q32),M23/C21),0) -> 0 | S32: =IF(SUM(E32:R32)<M23,IF((M23-SUM(E32:R32))<M23/C21,M23-SUM(E32:R32),M23/C21),0) -> 0 | T32: =IF(SUM(E32:S32)<M23,IF((M23-SUM(E32:S32))<M23/C21,M23-SUM(E32:S32),M23/C21),0) -> 0 | U32: =IF(SUM(E32:T32)<M23,IF((M23-SUM(E32:T32))<M23/C21,M23-SUM(E32:T32),M23/C21),0) -> 0 | V32: =IF(SUM(E32:U32)<M23,IF((M23-SUM(E32:U32))<M23/C21,M23-SUM(E32:U32),M23/C21),0) -> 0 | W32: =IF(SUM(E32:V32)<M23,IF((M23-SUM(E32:V32))<M23/C21,M23-SUM(E32:V32),M23/C21),0) -> 0 | X32: =IF(SUM(E32:W32)<M23,IF((M23-SUM(E32:W32))<M23/C21,M23-SUM(E32:W32),M23/C21),0) -> 0
B33: 第十年投资在各年的折旧 | D33: =SUM(E33:X33) -> 0 | N33: =O33*(1-N22/12) -> 0 | O33: =N23/C21 -> 0 | P33: =IF(SUM(E33:O33)<N23,IF((N23-SUM(E33:O33))<N23/C21,N23-SUM(E33:O33),N23/C21),0) -> 0 | Q33: =IF(SUM(E33:P33)<N23,IF((N23-SUM(E33:P33))<N23/C21,N23-SUM(E33:P33),N23/C21),0) -> 0 | R33: =IF(SUM(E33:Q33)<N23,IF((N23-SUM(E33:Q33))<N23/C21,N23-SUM(E33:Q33),N23/C21),0) -> 0 | S33: =IF(SUM(E33:R33)<N23,IF((N23-SUM(E33:R33))<N23/C21,N23-SUM(E33:R33),N23/C21),0) -> 0 | T33: =IF(SUM(E33:S33)<N23,IF((N23-SUM(E33:S33))<N23/C21,N23-SUM(E33:S33),N23/C21),0) -> 0 | U33: =IF(SUM(E33:T33)<N23,IF((N23-SUM(E33:T33))<N23/C21,N23-SUM(E33:T33),N23/C21),0) -> 0 | V33: =IF(SUM(E33:U33)<N23,IF((N23-SUM(E33:U33))<N23/C21,N23-SUM(E33:U33),N23/C21),0) -> 0 | W33: =IF(SUM(E33:V33)<N23,IF((N23-SUM(E33:V33))<N23/C21,N23-SUM(E33:V33),N23/C21),0) -> 0 | X33: =IF(SUM(E33:W33)<N23,IF((N23-SUM(E33:W33))<N23/C21,N23-SUM(E33:W33),N23/C21),0) -> 0
B34: 第十一年投资在各年的折旧 | D34: =SUM(E34:X34) -> 0 | O34: =P34*(1-O22/12) -> 0 | P34: =O23/C21 -> 0 | Q34: =IF(SUM(E34:P34)<O23,IF((O23-SUM(E34:P34))<O23/C21,O23-SUM(E34:P34),O23/C21),0) -> 0 | R34: =IF(SUM(E34:Q34)<O23,IF((O23-SUM(E34:Q34))<O23/C21,O23-SUM(E34:Q34),O23/C21),0) -> 0 | S34: =IF(SUM(E34:R34)<O23,IF((O23-SUM(E34:R34))<O23/C21,O23-SUM(E34:R34),O23/C21),0) -> 0 | T34: =IF(SUM(E34:S34)<O23,IF((O23-SUM(E34:S34))<O23/C21,O23-SUM(E34:S34),O23/C21),0) -> 0 | U34: =IF(SUM(E34:T34)<O23,IF((O23-SUM(E34:T34))<O23/C21,O23-SUM(E34:T34),O23/C21),0) -> 0 | V34: =IF(SUM(E34:U34)<O23,IF((O23-SUM(E34:U34))<O23/C21,O23-SUM(E34:U34),O23/C21),0) -> 0 | W34: =IF(SUM(E34:V34)<O23,IF((O23-SUM(E34:V34))<O23/C21,O23-SUM(E34:V34),O23/C21),0) -> 0 | X34: =IF(SUM(E34:W34)<O23,IF((O23-SUM(E34:W34))<O23/C21,O23-SUM(E34:W34),O23/C21),0) -> 0
B36: 光缆及管道类投资累计折旧 | D36: =SUM(E36:X36) -> 0 | E36: =SUM(E40:E50) -> 0 | F36: =SUM(F40:F50) -> 0 | G36: =SUM(G40:G50) -> 0 | H36: =SUM(H40:H50) -> 0 | I36: =SUM(I40:I50) -> 0 | J36: =SUM(J40:J50) -> 0 | K36: =SUM(K40:K50) -> 0 | L36: =SUM(L40:L50) -> 0 | ... X36: =SUM(X40:X50) -> 0
B37: 折旧年限 | C37: 10
B38: 当年投产月份 | E38: 0 | F38: 0 | G38: 0 | H38: 0 | I38: 0 | J38: 0 | K38: 0 | L38: 0 | M38: 0 | N38: 0 | O38: 0
B39: 各年光缆及管道类投资规模 | D39: =SUM(E39:O39) -> 0
B40: 第一年投资在各年的折旧 | D40: =SUM(E40:X40) -> 0 | E40: =F40*(1-E38/12) -> 0 | F40: =E39/C37 -> 0 | G40: =IF(SUM(E40:F40)<E39,IF((E39-SUM(E40:F40))<E39/C37,E39-SUM(E40:F40),E39/C37),0) -> 0 | H40: =IF(SUM(E40:G40)<E39,IF((E39-SUM(E40:G40))<E39/C37,E39-SUM(E40:G40),E39/C37),0) -> 0 | I40: =IF(SUM(E40:H40)<E39,IF((E39-SUM(E40:H40))<E39/C37,E39-SUM(E40:H40),E39/C37),0) -> 0 | J40: =IF(SUM(E40:I40)<E39,IF((E39-SUM(E40:I40))<E39/C37,E39-SUM(E40:I40),E39/C37),0) -> 0 | K40: =IF(SUM(E40:J40)<E39,IF((E39-SUM(E40:J40))<E39/C37,E39-SUM(E40:J40),E39/C37),0) -> 0 | L40: =IF(SUM(E40:K40)<E39,IF((E39-SUM(E40:K40))<E39/C37,E39-SUM(E40:K40),E39/C37),0) -> 0 | M40: =IF(SUM(E40:L40)<E39,IF((E39-SUM(E40:L40))<E39/C37,E39-SUM(E40:L40),E39/C37),0) -> 0 | N40: =IF(SUM(E40:M40)<E39,IF((E39-SUM(E40:M40))<E39/C37,E39-SUM(E40:M40),E39/C37),0) -> 0 | O40: =IF(SUM(E40:N40)<E39,IF((E39-SUM(E40:N40))<E39/C37,E39-SUM(E40:N40),E39/C37),0) -> 0 | P40: =IF(SUM(E40:O40)<E39,IF((E39-SUM(E40:O40))<E39/C37,E39-SUM(E40:O40),E39/C37),0) -> 0 | Q40: =IF(SUM(E40:P40)<E39,IF((E39-SUM(E40:P40))<E39/C37,E39-SUM(E40:P40),E39/C37),0) -> 0 | R40: =IF(SUM(E40:Q40)<E39,IF((E39-SUM(E40:Q40))<E39/C37,E39-SUM(E40:Q40),E39/C37),0) -> 0 | S40: =IF(SUM(E40:R40)<E39,IF((E39-SUM(E40:R40))<E39/C37,E39-SUM(E40:R40),E39/C37),0) -> 0 | T40: =IF(SUM(E40:S40)<E39,IF((E39-SUM(E40:S40))<E39/C37,E39-SUM(E40:S40),E39/C37),0) -> 0 | U40: =IF(SUM(E40:T40)<E39,IF((E39-SUM(E40:T40))<E39/C37,E39-SUM(E40:T40),E39/C37),0) -> 0 | V40: =IF(SUM(E40:U40)<E39,IF((E39-SUM(E40:U40))<E39/C37,E39-SUM(E40:U40),E39/C37),0) -> 0 | W40: =IF(SUM(E40:V40)<E39,IF((E39-SUM(E40:V40))<E39/C37,E39-SUM(E40:V40),E39/C37),0) -> 0 | X40: =IF(SUM(E40:W40)<E39,IF((E39-SUM(E40:W40))<E39/C37,E39-SUM(E40:W40),E39/C37),0) -> 0
B41: 第二年投资在各年的折旧 | D41: =SUM(E41:X41) -> 0 | F41: =G41*(1-F38/12) -> 0 | G41: =F39/C37 -> 0 | H41: =IF(SUM(E41:G41)<F39,IF((F39-SUM(E41:G41))<F39/C37,F39-SUM(E41:G41),F39/C37),0) -> 0 | I41: =IF(SUM(E41:H41)<F39,IF((F39-SUM(E41:H41))<F39/C37,F39-SUM(E41:H41),F39/C37),0) -> 0 | J41: =IF(SUM(E41:I41)<F39,IF((F39-SUM(E41:I41))<F39/C37,F39-SUM(E41:I41),F39/C37),0) -> 0 | K41: =IF(SUM(E41:J41)<F39,IF((F39-SUM(E41:J41))<F39/C37,F39-SUM(E41:J41),F39/C37),0) -> 0 | L41: =IF(SUM(E41:K41)<F39,IF((F39-SUM(E41:K41))<F39/C37,F39-SUM(E41:K41),F39/C37),0) -> 0 | M41: =IF(SUM(E41:L41)<F39,IF((F39-SUM(E41:L41))<F39/C37,F39-SUM(E41:L41),F39/C37),0) -> 0 | N41: =IF(SUM(E41:M41)<F39,IF((F39-SUM(E41:M41))<F39/C37,F39-SUM(E41:M41),F39/C37),0) -> 0 | O41: =IF(SUM(E41:N41)<F39,IF((F39-SUM(E41:N41))<F39/C37,F39-SUM(E41:N41),F39/C37),0) -> 0 | P41: =IF(SUM(E41:O41)<F39,IF((F39-SUM(E41:O41))<F39/C37,F39-SUM(E41:O41),F39/C37),0) -> 0 | Q41: =IF(SUM(E41:P41)<F39,IF((F39-SUM(E41:P41))<F39/C37,F39-SUM(E41:P41),F39/C37),0) -> 0 | R41: =IF(SUM(E41:Q41)<F39,IF((F39-SUM(E41:Q41))<F39/C37,F39-SUM(E41:Q41),F39/C37),0) -> 0 | S41: =IF(SUM(E41:R41)<F39,IF((F39-SUM(E41:R41))<F39/C37,F39-SUM(E41:R41),F39/C37),0) -> 0 | T41: =IF(SUM(E41:S41)<F39,IF((F39-SUM(E41:S41))<F39/C37,F39-SUM(E41:S41),F39/C37),0) -> 0 | U41: =IF(SUM(E41:T41)<F39,IF((F39-SUM(E41:T41))<F39/C37,F39-SUM(E41:T41),F39/C37),0) -> 0 | V41: =IF(SUM(E41:U41)<F39,IF((F39-SUM(E41:U41))<F39/C37,F39-SUM(E41:U41),F39/C37),0) -> 0 | W41: =IF(SUM(E41:V41)<F39,IF((F39-SUM(E41:V41))<F39/C37,F39-SUM(E41:V41),F39/C37),0) -> 0 | X41: =IF(SUM(E41:W41)<F39,IF((F39-SUM(E41:W41))<F39/C37,F39-SUM(E41:W41),F39/C37),0) -> 0
B42: 第三年投资在各年的折旧 | D42: =SUM(E42:X42) -> 0 | G42: =H42*(1-G38/12) -> 0 | H42: =G39/C37 -> 0 | I42: =IF(SUM(E42:H42)<G39,IF((G39-SUM(E42:H42))<G39/C37,G39-SUM(E42:H42),G39/C37),0) -> 0 | J42: =IF(SUM(E42:I42)<G39,IF((G39-SUM(E42:I42))<G39/C37,G39-SUM(E42:I42),G39/C37),0) -> 0 | K42: =IF(SUM(E42:J42)<G39,IF((G39-SUM(E42:J42))<G39/C37,G39-SUM(E42:J42),G39/C37),0) -> 0 | L42: =IF(SUM(E42:K42)<G39,IF((G39-SUM(E42:K42))<G39/C37,G39-SUM(E42:K42),G39/C37),0) -> 0 | M42: =IF(SUM(E42:L42)<G39,IF((G39-SUM(E42:L42))<G39/C37,G39-SUM(E42:L42),G39/C37),0) -> 0 | N42: =IF(SUM(E42:M42)<G39,IF((G39-SUM(E42:M42))<G39/C37,G39-SUM(E42:M42),G39/C37),0) -> 0 | O42: =IF(SUM(E42:N42)<G39,IF((G39-SUM(E42:N42))<G39/C37,G39-SUM(E42:N42),G39/C37),0) -> 0 | P42: =IF(SUM(E42:O42)<G39,IF((G39-SUM(E42:O42))<G39/C37,G39-SUM(E42:O42),G39/C37),0) -> 0 | Q42: =IF(SUM(E42:P42)<G39,IF((G39-SUM(E42:P42))<G39/C37,G39-SUM(E42:P42),G39/C37),0) -> 0 | R42: =IF(SUM(E42:Q42)<G39,IF((G39-SUM(E42:Q42))<G39/C37,G39-SUM(E42:Q42),G39/C37),0) -> 0 | S42: =IF(SUM(E42:R42)<G39,IF((G39-SUM(E42:R42))<G39/C37,G39-SUM(E42:R42),G39/C37),0) -> 0 | T42: =IF(SUM(E42:S42)<G39,IF((G39-SUM(E42:S42))<G39/C37,G39-SUM(E42:S42),G39/C37),0) -> 0 | U42: =IF(SUM(E42:T42)<G39,IF((G39-SUM(E42:T42))<G39/C37,G39-SUM(E42:T42),G39/C37),0) -> 0 | V42: =IF(SUM(E42:U42)<G39,IF((G39-SUM(E42:U42))<G39/C37,G39-SUM(E42:U42),G39/C37),0) -> 0 | W42: =IF(SUM(E42:V42)<G39,IF((G39-SUM(E42:V42))<G39/C37,G39-SUM(E42:V42),G39/C37),0) -> 0 | X42: =IF(SUM(E42:W42)<G39,IF((G39-SUM(E42:W42))<G39/C37,G39-SUM(E42:W42),G39/C37),0) -> 0
B43: 第四年投资在各年的折旧 | D43: =SUM(E43:X43) -> 0 | H43: =I43*(1-H38/12) -> 0 | I43: =H39/C37 -> 0 | J43: =IF(SUM(E43:I43)<H39,IF((H39-SUM(E43:I43))<H39/C37,H39-SUM(E43:I43),H39/C37),0) -> 0 | K43: =IF(SUM(E43:J43)<H39,IF((H39-SUM(E43:J43))<H39/C37,H39-SUM(E43:J43),H39/C37),0) -> 0 | L43: =IF(SUM(E43:K43)<H39,IF((H39-SUM(E43:K43))<H39/C37,H39-SUM(E43:K43),H39/C37),0) -> 0 | M43: =IF(SUM(E43:L43)<H39,IF((H39-SUM(E43:L43))<H39/C37,H39-SUM(E43:L43),H39/C37),0) -> 0 | N43: =IF(SUM(E43:M43)<H39,IF((H39-SUM(E43:M43))<H39/C37,H39-SUM(E43:M43),H39/C37),0) -> 0 | O43: =IF(SUM(E43:N43)<H39,IF((H39-SUM(E43:N43))<H39/C37,H39-SUM(E43:N43),H39/C37),0) -> 0 | P43: =IF(SUM(E43:O43)<H39,IF((H39-SUM(E43:O43))<H39/C37,H39-SUM(E43:O43),H39/C37),0) -> 0 | Q43: =IF(SUM(E43:P43)<H39,IF((H39-SUM(E43:P43))<H39/C37,H39-SUM(E43:P43),H39/C37),0) -> 0 | R43: =IF(SUM(E43:Q43)<H39,IF((H39-SUM(E43:Q43))<H39/C37,H39-SUM(E43:Q43),H39/C37),0) -> 0 | S43: =IF(SUM(E43:R43)<H39,IF((H39-SUM(E43:R43))<H39/C37,H39-SUM(E43:R43),H39/C37),0) -> 0 | T43: =IF(SUM(E43:S43)<H39,IF((H39-SUM(E43:S43))<H39/C37,H39-SUM(E43:S43),H39/C37),0) -> 0 | U43: =IF(SUM(E43:T43)<H39,IF((H39-SUM(E43:T43))<H39/C37,H39-SUM(E43:T43),H39/C37),0) -> 0 | V43: =IF(SUM(E43:U43)<H39,IF((H39-SUM(E43:U43))<H39/C37,H39-SUM(E43:U43),H39/C37),0) -> 0 | W43: =IF(SUM(E43:V43)<H39,IF((H39-SUM(E43:V43))<H39/C37,H39-SUM(E43:V43),H39/C37),0) -> 0 | X43: =IF(SUM(E43:W43)<H39,IF((H39-SUM(E43:W43))<H39/C37,H39-SUM(E43:W43),H39/C37),0) -> 0
B44: 第五年投资在各年的折旧 | D44: =SUM(E44:X44) -> 0 | I44: =J44*(1-I38/12) -> 0 | J44: =I39/C37 -> 0 | K44: =IF(SUM(E44:J44)<I39,IF((I39-SUM(E44:J44))<I39/C37,I39-SUM(E44:J44),I39/C37),0) -> 0 | L44: =IF(SUM(E44:K44)<I39,IF((I39-SUM(E44:K44))<I39/C37,I39-SUM(E44:K44),I39/C37),0) -> 0 | M44: =IF(SUM(E44:L44)<I39,IF((I39-SUM(E44:L44))<I39/C37,I39-SUM(E44:L44),I39/C37),0) -> 0 | N44: =IF(SUM(E44:M44)<I39,IF((I39-SUM(E44:M44))<I39/C37,I39-SUM(E44:M44),I39/C37),0) -> 0 | O44: =IF(SUM(E44:N44)<I39,IF((I39-SUM(E44:N44))<I39/C37,I39-SUM(E44:N44),I39/C37),0) -> 0 | P44: =IF(SUM(E44:O44)<I39,IF((I39-SUM(E44:O44))<I39/C37,I39-SUM(E44:O44),I39/C37),0) -> 0 | Q44: =IF(SUM(E44:P44)<I39,IF((I39-SUM(E44:P44))<I39/C37,I39-SUM(E44:P44),I39/C37),0) -> 0 | R44: =IF(SUM(E44:Q44)<I39,IF((I39-SUM(E44:Q44))<I39/C37,I39-SUM(E44:Q44),I39/C37),0) -> 0 | S44: =IF(SUM(E44:R44)<I39,IF((I39-SUM(E44:R44))<I39/C37,I39-SUM(E44:R44),I39/C37),0) -> 0 | T44: =IF(SUM(E44:S44)<I39,IF((I39-SUM(E44:S44))<I39/C37,I39-SUM(E44:S44),I39/C37),0) -> 0 | U44: =IF(SUM(E44:T44)<I39,IF((I39-SUM(E44:T44))<I39/C37,I39-SUM(E44:T44),I39/C37),0) -> 0 | V44: =IF(SUM(E44:U44)<I39,IF((I39-SUM(E44:U44))<I39/C37,I39-SUM(E44:U44),I39/C37),0) -> 0 | W44: =IF(SUM(E44:V44)<I39,IF((I39-SUM(E44:V44))<I39/C37,I39-SUM(E44:V44),I39/C37),0) -> 0 | X44: =IF(SUM(E44:W44)<I39,IF((I39-SUM(E44:W44))<I39/C37,I39-SUM(E44:W44),I39/C37),0) -> 0
B45: 第六年投资在各年的折旧 | D45: =SUM(E45:X45) -> 0 | J45: =K45*(1-J38/12) -> 0 | K45: =J39/C37 -> 0 | L45: =IF(SUM(E45:K45)<J39,IF((J39-SUM(E45:K45))<J39/C37,J39-SUM(E45:K45),J39/C37),0) -> 0 | M45: =IF(SUM(E45:L45)<J39,IF((J39-SUM(E45:L45))<J39/C37,J39-SUM(E45:L45),J39/C37),0) -> 0 | N45: =IF(SUM(E45:M45)<J39,IF((J39-SUM(E45:M45))<J39/C37,J39-SUM(E45:M45),J39/C37),0) -> 0 | O45: =IF(SUM(E45:N45)<J39,IF((J39-SUM(E45:N45))<J39/C37,J39-SUM(E45:N45),J39/C37),0) -> 0 | P45: =IF(SUM(E45:O45)<J39,IF((J39-SUM(E45:O45))<J39/C37,J39-SUM(E45:O45),J39/C37),0) -> 0 | Q45: =IF(SUM(E45:P45)<J39,IF((J39-SUM(E45:P45))<J39/C37,J39-SUM(E45:P45),J39/C37),0) -> 0 | R45: =IF(SUM(E45:Q45)<J39,IF((J39-SUM(E45:Q45))<J39/C37,J39-SUM(E45:Q45),J39/C37),0) -> 0 | S45: =IF(SUM(E45:R45)<J39,IF((J39-SUM(E45:R45))<J39/C37,J39-SUM(E45:R45),J39/C37),0) -> 0 | T45: =IF(SUM(E45:S45)<J39,IF((J39-SUM(E45:S45))<J39/C37,J39-SUM(E45:S45),J39/C37),0) -> 0 | U45: =IF(SUM(E45:T45)<J39,IF((J39-SUM(E45:T45))<J39/C37,J39-SUM(E45:T45),J39/C37),0) -> 0 | V45: =IF(SUM(E45:U45)<J39,IF((J39-SUM(E45:U45))<J39/C37,J39-SUM(E45:U45),J39/C37),0) -> 0 | W45: =IF(SUM(E45:V45)<J39,IF((J39-SUM(E45:V45))<J39/C37,J39-SUM(E45:V45),J39/C37),0) -> 0 | X45: =IF(SUM(E45:W45)<J39,IF((J39-SUM(E45:W45))<J39/C37,J39-SUM(E45:W45),J39/C37),0) -> 0
B46: 第七年投资在各年的折旧 | D46: =SUM(E46:X46) -> 0 | K46: =L46*(1-K38/12) -> 0 | L46: =K39/C37 -> 0 | M46: =IF(SUM(E46:L46)<K39,IF((K39-SUM(E46:L46))<K39/C37,K39-SUM(E46:L46),K39/C37),0) -> 0 | N46: =IF(SUM(E46:M46)<K39,IF((K39-SUM(E46:M46))<K39/C37,K39-SUM(E46:M46),K39/C37),0) -> 0 | O46: =IF(SUM(E46:N46)<K39,IF((K39-SUM(E46:N46))<K39/C37,K39-SUM(E46:N46),K39/C37),0) -> 0 | P46: =IF(SUM(E46:O46)<K39,IF((K39-SUM(E46:O46))<K39/C37,K39-SUM(E46:O46),K39/C37),0) -> 0 | Q46: =IF(SUM(E46:P46)<K39,IF((K39-SUM(E46:P46))<K39/C37,K39-SUM(E46:P46),K39/C37),0) -> 0 | R46: =IF(SUM(E46:Q46)<K39,IF((K39-SUM(E46:Q46))<K39/C37,K39-SUM(E46:Q46),K39/C37),0) -> 0 | S46: =IF(SUM(E46:R46)<K39,IF((K39-SUM(E46:R46))<K39/C37,K39-SUM(E46:R46),K39/C37),0) -> 0 | T46: =IF(SUM(E46:S46)<K39,IF((K39-SUM(E46:S46))<K39/C37,K39-SUM(E46:S46),K39/C37),0) -> 0 | U46: =IF(SUM(E46:T46)<K39,IF((K39-SUM(E46:T46))<K39/C37,K39-SUM(E46:T46),K39/C37),0) -> 0 | V46: =IF(SUM(E46:U46)<K39,IF((K39-SUM(E46:U46))<K39/C37,K39-SUM(E46:U46),K39/C37),0) -> 0 | W46: =IF(SUM(E46:V46)<K39,IF((K39-SUM(E46:V46))<K39/C37,K39-SUM(E46:V46),K39/C37),0) -> 0 | X46: =IF(SUM(E46:W46)<K39,IF((K39-SUM(E46:W46))<K39/C37,K39-SUM(E46:W46),K39/C37),0) -> 0
B47: 第八年投资在各年的折旧 | D47: =SUM(E47:X47) -> 0 | L47: =M47*(1-L38/12) -> 0 | M47: =L39/C37 -> 0 | N47: =IF(SUM(E47:M47)<L39,IF((L39-SUM(E47:M47))<L39/C37,L39-SUM(E47:M47),L39/C37),0) -> 0 | O47: =IF(SUM(E47:N47)<L39,IF((L39-SUM(E47:N47))<L39/C37,L39-SUM(E47:N47),L39/C37),0) -> 0 | P47: =IF(SUM(E47:O47)<L39,IF((L39-SUM(E47:O47))<L39/C37,L39-SUM(E47:O47),L39/C37),0) -> 0 | Q47: =IF(SUM(E47:P47)<L39,IF((L39-SUM(E47:P47))<L39/C37,L39-SUM(E47:P47),L39/C37),0) -> 0 | R47: =IF(SUM(E47:Q47)<L39,IF((L39-SUM(E47:Q47))<L39/C37,L39-SUM(E47:Q47),L39/C37),0) -> 0 | S47: =IF(SUM(E47:R47)<L39,IF((L39-SUM(E47:R47))<L39/C37,L39-SUM(E47:R47),L39/C37),0) -> 0 | T47: =IF(SUM(E47:S47)<L39,IF((L39-SUM(E47:S47))<L39/C37,L39-SUM(E47:S47),L39/C37),0) -> 0 | U47: =IF(SUM(E47:T47)<L39,IF((L39-SUM(E47:T47))<L39/C37,L39-SUM(E47:T47),L39/C37),0) -> 0 | V47: =IF(SUM(E47:U47)<L39,IF((L39-SUM(E47:U47))<L39/C37,L39-SUM(E47:U47),L39/C37),0) -> 0 | W47: =IF(SUM(E47:V47)<L39,IF((L39-SUM(E47:V47))<L39/C37,L39-SUM(E47:V47),L39/C37),0) -> 0 | X47: =IF(SUM(E47:W47)<L39,IF((L39-SUM(E47:W47))<L39/C37,L39-SUM(E47:W47),L39/C37),0) -> 0
B48: 第九年投资在各年的折旧 | D48: =SUM(E48:X48) -> 0 | M48: =N48*(1-M38/12) -> 0 | N48: =M39/C37 -> 0 | O48: =IF(SUM(E48:N48)<M39,IF((M39-SUM(E48:N48))<M39/C37,M39-SUM(E48:N48),M39/C37),0) -> 0 | P48: =IF(SUM(E48:O48)<M39,IF((M39-SUM(E48:O48))<M39/C37,M39-SUM(E48:O48),M39/C37),0) -> 0 | Q48: =IF(SUM(E48:P48)<M39,IF((M39-SUM(E48:P48))<M39/C37,M39-SUM(E48:P48),M39/C37),0) -> 0 | R48: =IF(SUM(E48:Q48)<M39,IF((M39-SUM(E48:Q48))<M39/C37,M39-SUM(E48:Q48),M39/C37),0) -> 0 | S48: =IF(SUM(E48:R48)<M39,IF((M39-SUM(E48:R48))<M39/C37,M39-SUM(E48:R48),M39/C37),0) -> 0 | T48: =IF(SUM(E48:S48)<M39,IF((M39-SUM(E48:S48))<M39/C37,M39-SUM(E48:S48),M39/C37),0) -> 0 | U48: =IF(SUM(E48:T48)<M39,IF((M39-SUM(E48:T48))<M39/C37,M39-SUM(E48:T48),M39/C37),0) -> 0 | V48: =IF(SUM(E48:U48)<M39,IF((M39-SUM(E48:U48))<M39/C37,M39-SUM(E48:U48),M39/C37),0) -> 0 | W48: =IF(SUM(E48:V48)<M39,IF((M39-SUM(E48:V48))<M39/C37,M39-SUM(E48:V48),M39/C37),0) -> 0 | X48: =IF(SUM(E48:W48)<M39,IF((M39-SUM(E48:W48))<M39/C37,M39-SUM(E48:W48),M39/C37),0) -> 0
B49: 第十年投资在各年的折旧 | D49: =SUM(E49:X49) -> 0 | N49: =O49*(1-N38/12) -> 0 | O49: =N39/C37 -> 0 | P49: =IF(SUM(E49:O49)<N39,IF((N39-SUM(E49:O49))<N39/C37,N39-SUM(E49:O49),N39/C37),0) -> 0 | Q49: =IF(SUM(E49:P49)<N39,IF((N39-SUM(E49:P49))<N39/C37,N39-SUM(E49:P49),N39/C37),0) -> 0 | R49: =IF(SUM(E49:Q49)<N39,IF((N39-SUM(E49:Q49))<N39/C37,N39-SUM(E49:Q49),N39/C37),0) -> 0 | S49: =IF(SUM(E49:R49)<N39,IF((N39-SUM(E49:R49))<N39/C37,N39-SUM(E49:R49),N39/C37),0) -> 0 | T49: =IF(SUM(E49:S49)<N39,IF((N39-SUM(E49:S49))<N39/C37,N39-SUM(E49:S49),N39/C37),0) -> 0 | U49: =IF(SUM(E49:T49)<N39,IF((N39-SUM(E49:T49))<N39/C37,N39-SUM(E49:T49),N39/C37),0) -> 0 | V49: =IF(SUM(E49:U49)<N39,IF((N39-SUM(E49:U49))<N39/C37,N39-SUM(E49:U49),N39/C37),0) -> 0 | W49: =IF(SUM(E49:V49)<N39,IF((N39-SUM(E49:V49))<N39/C37,N39-SUM(E49:V49),N39/C37),0) -> 0 | X49: =IF(SUM(E49:W49)<N39,IF((N39-SUM(E49:W49))<N39/C37,N39-SUM(E49:W49),N39/C37),0) -> 0
B50: 第十一年投资在各年的折旧 | D50: =SUM(E50:X50) -> 0 | O50: =P50*(1-O38/12) -> 0 | P50: =O39/C37 -> 0 | Q50: =IF(SUM(E50:P50)<O39,IF((O39-SUM(E50:P50))<O39/C37,O39-SUM(E50:P50),O39/C37),0) -> 0 | R50: =IF(SUM(E50:Q50)<O39,IF((O39-SUM(E50:Q50))<O39/C37,O39-SUM(E50:Q50),O39/C37),0) -> 0 | S50: =IF(SUM(E50:R50)<O39,IF((O39-SUM(E50:R50))<O39/C37,O39-SUM(E50:R50),O39/C37),0) -> 0 | T50: =IF(SUM(E50:S50)<O39,IF((O39-SUM(E50:S50))<O39/C37,O39-SUM(E50:S50),O39/C37),0) -> 0 | U50: =IF(SUM(E50:T50)<O39,IF((O39-SUM(E50:T50))<O39/C37,O39-SUM(E50:T50),O39/C37),0) -> 0 | V50: =IF(SUM(E50:U50)<O39,IF((O39-SUM(E50:U50))<O39/C37,O39-SUM(E50:U50),O39/C37),0) -> 0 | W50: =IF(SUM(E50:V50)<O39,IF((O39-SUM(E50:V50))<O39/C37,O39-SUM(E50:V50),O39/C37),0) -> 0 | X50: =IF(SUM(E50:W50)<O39,IF((O39-SUM(E50:W50))<O39/C37,O39-SUM(E50:W50),O39/C37),0) -> 0
B52: 软件类投资累计摊销 | D52: =SUM(E52:X52) -> 0 | E52: =SUM(E56:E66) -> 0 | F52: =SUM(F56:F66) -> 0 | G52: =SUM(G56:G66) -> 0 | H52: =SUM(H56:H66) -> 0 | I52: =SUM(I56:I66) -> 0 | J52: =SUM(J56:J66) -> 0 | K52: =SUM(K56:K66) -> 0 | L52: =SUM(L56:L66) -> 0 | ... X52: =SUM(X56:X66) -> 0
B53: 摊销年限 | C53: 5
B54: 当年投产月份 | E54: 0 | F54: 0 | G54: 0 | H54: 0 | I54: 0 | J54: 0 | K54: 0 | L54: 0 | M54: 0 | N54: 0 | O54: 0
B55: 各年软件类投资规模 | D55: =SUM(E55:O55) -> 0
B56: 第一年投资在各年的折旧 | D56: =SUM(E56:X56) -> 0 | E56: =F56*(1-E54/12) -> 0 | F56: =E55/C53 -> 0 | G56: =IF(SUM(E56:F56)<E55,IF((E55-SUM(E56:F56))<E55/C53,E55-SUM(E56:F56),E55/C53),0) -> 0 | H56: =IF(SUM(E56:G56)<E55,IF((E55-SUM(E56:G56))<E55/C53,E55-SUM(E56:G56),E55/C53),0) -> 0 | I56: =IF(SUM(E56:H56)<E55,IF((E55-SUM(E56:H56))<E55/C53,E55-SUM(E56:H56),E55/C53),0) -> 0 | J56: =IF(SUM(E56:I56)<E55,IF((E55-SUM(E56:I56))<E55/C53,E55-SUM(E56:I56),E55/C53),0) -> 0 | K56: =IF(SUM(E56:J56)<E55,IF((E55-SUM(E56:J56))<E55/C53,E55-SUM(E56:J56),E55/C53),0) -> 0 | L56: =IF(SUM(E56:K56)<E55,IF((E55-SUM(E56:K56))<E55/C53,E55-SUM(E56:K56),E55/C53),0) -> 0 | M56: =IF(SUM(E56:L56)<E55,IF((E55-SUM(E56:L56))<E55/C53,E55-SUM(E56:L56),E55/C53),0) -> 0 | N56: =IF(SUM(E56:M56)<E55,IF((E55-SUM(E56:M56))<E55/C53,E55-SUM(E56:M56),E55/C53),0) -> 0 | O56: =IF(SUM(E56:N56)<E55,IF((E55-SUM(E56:N56))<E55/C53,E55-SUM(E56:N56),E55/C53),0) -> 0 | P56: =IF(SUM(E56:O56)<E55,IF((E55-SUM(E56:O56))<E55/C53,E55-SUM(E56:O56),E55/C53),0) -> 0 | Q56: =IF(SUM(E56:P56)<E55,IF((E55-SUM(E56:P56))<E55/C53,E55-SUM(E56:P56),E55/C53),0) -> 0 | R56: =IF(SUM(E56:Q56)<E55,IF((E55-SUM(E56:Q56))<E55/C53,E55-SUM(E56:Q56),E55/C53),0) -> 0 | S56: =IF(SUM(E56:R56)<E55,IF((E55-SUM(E56:R56))<E55/C53,E55-SUM(E56:R56),E55/C53),0) -> 0 | T56: =IF(SUM(E56:S56)<E55,IF((E55-SUM(E56:S56))<E55/C53,E55-SUM(E56:S56),E55/C53),0) -> 0 | U56: =IF(SUM(E56:T56)<E55,IF((E55-SUM(E56:T56))<E55/C53,E55-SUM(E56:T56),E55/C53),0) -> 0 | V56: =IF(SUM(E56:U56)<E55,IF((E55-SUM(E56:U56))<E55/C53,E55-SUM(E56:U56),E55/C53),0) -> 0 | W56: =IF(SUM(E56:V56)<E55,IF((E55-SUM(E56:V56))<E55/C53,E55-SUM(E56:V56),E55/C53),0) -> 0 | X56: =IF(SUM(E56:W56)<E55,IF((E55-SUM(E56:W56))<E55/C53,E55-SUM(E56:W56),E55/C53),0) -> 0
B57: 第二年投资在各年的折旧 | D57: =SUM(E57:X57) -> 0 | F57: =G57*(1-F54/12) -> 0 | G57: =F55/C53 -> 0 | H57: =IF(SUM(E57:G57)<F55,IF((F55-SUM(E57:G57))<F55/C53,F55-SUM(E57:G57),F55/C53),0) -> 0 | I57: =IF(SUM(E57:H57)<F55,IF((F55-SUM(E57:H57))<F55/C53,F55-SUM(E57:H57),F55/C53),0) -> 0 | J57: =IF(SUM(E57:I57)<F55,IF((F55-SUM(E57:I57))<F55/C53,F55-SUM(E57:I57),F55/C53),0) -> 0 | K57: =IF(SUM(E57:J57)<F55,IF((F55-SUM(E57:J57))<F55/C53,F55-SUM(E57:J57),F55/C53),0) -> 0 | L57: =IF(SUM(E57:K57)<F55,IF((F55-SUM(E57:K57))<F55/C53,F55-SUM(E57:K57),F55/C53),0) -> 0 | M57: =IF(SUM(E57:L57)<F55,IF((F55-SUM(E57:L57))<F55/C53,F55-SUM(E57:L57),F55/C53),0) -> 0 | N57: =IF(SUM(E57:M57)<F55,IF((F55-SUM(E57:M57))<F55/C53,F55-SUM(E57:M57),F55/C53),0) -> 0 | O57: =IF(SUM(E57:N57)<F55,IF((F55-SUM(E57:N57))<F55/C53,F55-SUM(E57:N57),F55/C53),0) -> 0 | P57: =IF(SUM(E57:O57)<F55,IF((F55-SUM(E57:O57))<F55/C53,F55-SUM(E57:O57),F55/C53),0) -> 0 | Q57: =IF(SUM(E57:P57)<F55,IF((F55-SUM(E57:P57))<F55/C53,F55-SUM(E57:P57),F55/C53),0) -> 0 | R57: =IF(SUM(E57:Q57)<F55,IF((F55-SUM(E57:Q57))<F55/C53,F55-SUM(E57:Q57),F55/C53),0) -> 0 | S57: =IF(SUM(E57:R57)<F55,IF((F55-SUM(E57:R57))<F55/C53,F55-SUM(E57:R57),F55/C53),0) -> 0 | T57: =IF(SUM(E57:S57)<F55,IF((F55-SUM(E57:S57))<F55/C53,F55-SUM(E57:S57),F55/C53),0) -> 0 | U57: =IF(SUM(E57:T57)<F55,IF((F55-SUM(E57:T57))<F55/C53,F55-SUM(E57:T57),F55/C53),0) -> 0 | V57: =IF(SUM(E57:U57)<F55,IF((F55-SUM(E57:U57))<F55/C53,F55-SUM(E57:U57),F55/C53),0) -> 0 | W57: =IF(SUM(E57:V57)<F55,IF((F55-SUM(E57:V57))<F55/C53,F55-SUM(E57:V57),F55/C53),0) -> 0 | X57: =IF(SUM(E57:W57)<F55,IF((F55-SUM(E57:W57))<F55/C53,F55-SUM(E57:W57),F55/C53),0) -> 0
B58: 第三年投资在各年的折旧 | D58: =SUM(E58:X58) -> 0 | G58: =H58*(1-G54/12) -> 0 | H58: =G55/C53 -> 0 | I58: =IF(SUM(E58:H58)<G55,IF((G55-SUM(E58:H58))<G55/C53,G55-SUM(E58:H58),G55/C53),0) -> 0 | J58: =IF(SUM(E58:I58)<G55,IF((G55-SUM(E58:I58))<G55/C53,G55-SUM(E58:I58),G55/C53),0) -> 0 | K58: =IF(SUM(E58:J58)<G55,IF((G55-SUM(E58:J58))<G55/C53,G55-SUM(E58:J58),G55/C53),0) -> 0 | L58: =IF(SUM(E58:K58)<G55,IF((G55-SUM(E58:K58))<G55/C53,G55-SUM(E58:K58),G55/C53),0) -> 0 | M58: =IF(SUM(E58:L58)<G55,IF((G55-SUM(E58:L58))<G55/C53,G55-SUM(E58:L58),G55/C53),0) -> 0 | N58: =IF(SUM(E58:M58)<G55,IF((G55-SUM(E58:M58))<G55/C53,G55-SUM(E58:M58),G55/C53),0) -> 0 | O58: =IF(SUM(E58:N58)<G55,IF((G55-SUM(E58:N58))<G55/C53,G55-SUM(E58:N58),G55/C53),0) -> 0 | P58: =IF(SUM(E58:O58)<G55,IF((G55-SUM(E58:O58))<G55/C53,G55-SUM(E58:O58),G55/C53),0) -> 0 | Q58: =IF(SUM(E58:P58)<G55,IF((G55-SUM(E58:P58))<G55/C53,G55-SUM(E58:P58),G55/C53),0) -> 0 | R58: =IF(SUM(E58:Q58)<G55,IF((G55-SUM(E58:Q58))<G55/C53,G55-SUM(E58:Q58),G55/C53),0) -> 0 | S58: =IF(SUM(E58:R58)<G55,IF((G55-SUM(E58:R58))<G55/C53,G55-SUM(E58:R58),G55/C53),0) -> 0 | T58: =IF(SUM(E58:S58)<G55,IF((G55-SUM(E58:S58))<G55/C53,G55-SUM(E58:S58),G55/C53),0) -> 0 | U58: =IF(SUM(E58:T58)<G55,IF((G55-SUM(E58:T58))<G55/C53,G55-SUM(E58:T58),G55/C53),0) -> 0 | V58: =IF(SUM(E58:U58)<G55,IF((G55-SUM(E58:U58))<G55/C53,G55-SUM(E58:U58),G55/C53),0) -> 0 | W58: =IF(SUM(E58:V58)<G55,IF((G55-SUM(E58:V58))<G55/C53,G55-SUM(E58:V58),G55/C53),0) -> 0 | X58: =IF(SUM(E58:W58)<G55,IF((G55-SUM(E58:W58))<G55/C53,G55-SUM(E58:W58),G55/C53),0) -> 0
B59: 第四年投资在各年的折旧 | D59: =SUM(E59:X59) -> 0 | H59: =I59*(1-H54/12) -> 0 | I59: =H55/C53 -> 0 | J59: =IF(SUM(E59:I59)<H55,IF((H55-SUM(E59:I59))<H55/C53,H55-SUM(E59:I59),H55/C53),0) -> 0 | K59: =IF(SUM(E59:J59)<H55,IF((H55-SUM(E59:J59))<H55/C53,H55-SUM(E59:J59),H55/C53),0) -> 0 | L59: =IF(SUM(E59:K59)<H55,IF((H55-SUM(E59:K59))<H55/C53,H55-SUM(E59:K59),H55/C53),0) -> 0 | M59: =IF(SUM(E59:L59)<H55,IF((H55-SUM(E59:L59))<H55/C53,H55-SUM(E59:L59),H55/C53),0) -> 0 | N59: =IF(SUM(E59:M59)<H55,IF((H55-SUM(E59:M59))<H55/C53,H55-SUM(E59:M59),H55/C53),0) -> 0 | O59: =IF(SUM(E59:N59)<H55,IF((H55-SUM(E59:N59))<H55/C53,H55-SUM(E59:N59),H55/C53),0) -> 0 | P59: =IF(SUM(E59:O59)<H55,IF((H55-SUM(E59:O59))<H55/C53,H55-SUM(E59:O59),H55/C53),0) -> 0 | Q59: =IF(SUM(E59:P59)<H55,IF((H55-SUM(E59:P59))<H55/C53,H55-SUM(E59:P59),H55/C53),0) -> 0 | R59: =IF(SUM(E59:Q59)<H55,IF((H55-SUM(E59:Q59))<H55/C53,H55-SUM(E59:Q59),H55/C53),0) -> 0 | S59: =IF(SUM(E59:R59)<H55,IF((H55-SUM(E59:R59))<H55/C53,H55-SUM(E59:R59),H55/C53),0) -> 0 | T59: =IF(SUM(E59:S59)<H55,IF((H55-SUM(E59:S59))<H55/C53,H55-SUM(E59:S59),H55/C53),0) -> 0 | U59: =IF(SUM(E59:T59)<H55,IF((H55-SUM(E59:T59))<H55/C53,H55-SUM(E59:T59),H55/C53),0) -> 0 | V59: =IF(SUM(E59:U59)<H55,IF((H55-SUM(E59:U59))<H55/C53,H55-SUM(E59:U59),H55/C53),0) -> 0 | W59: =IF(SUM(E59:V59)<H55,IF((H55-SUM(E59:V59))<H55/C53,H55-SUM(E59:V59),H55/C53),0) -> 0 | X59: =IF(SUM(E59:W59)<H55,IF((H55-SUM(E59:W59))<H55/C53,H55-SUM(E59:W59),H55/C53),0) -> 0
B60: 第五年投资在各年的折旧 | D60: =SUM(E60:X60) -> 0 | I60: =J60*(1-I54/12) -> 0 | J60: =I55/C53 -> 0 | K60: =IF(SUM(E60:J60)<I55,IF((I55-SUM(E60:J60))<I55/C53,I55-SUM(E60:J60),I55/C53),0) -> 0 | L60: =IF(SUM(E60:K60)<I55,IF((I55-SUM(E60:K60))<I55/C53,I55-SUM(E60:K60),I55/C53),0) -> 0 | M60: =IF(SUM(E60:L60)<I55,IF((I55-SUM(E60:L60))<I55/C53,I55-SUM(E60:L60),I55/C53),0) -> 0 | N60: =IF(SUM(E60:M60)<I55,IF((I55-SUM(E60:M60))<I55/C53,I55-SUM(E60:M60),I55/C53),0) -> 0 | O60: =IF(SUM(E60:N60)<I55,IF((I55-SUM(E60:N60))<I55/C53,I55-SUM(E60:N60),I55/C53),0) -> 0 | P60: =IF(SUM(E60:O60)<I55,IF((I55-SUM(E60:O60))<I55/C53,I55-SUM(E60:O60),I55/C53),0) -> 0 | Q60: =IF(SUM(E60:P60)<I55,IF((I55-SUM(E60:P60))<I55/C53,I55-SUM(E60:P60),I55/C53),0) -> 0 | R60: =IF(SUM(E60:Q60)<I55,IF((I55-SUM(E60:Q60))<I55/C53,I55-SUM(E60:Q60),I55/C53),0) -> 0 | S60: =IF(SUM(E60:R60)<I55,IF((I55-SUM(E60:R60))<I55/C53,I55-SUM(E60:R60),I55/C53),0) -> 0 | T60: =IF(SUM(E60:S60)<I55,IF((I55-SUM(E60:S60))<I55/C53,I55-SUM(E60:S60),I55/C53),0) -> 0 | U60: =IF(SUM(E60:T60)<I55,IF((I55-SUM(E60:T60))<I55/C53,I55-SUM(E60:T60),I55/C53),0) -> 0 | V60: =IF(SUM(E60:U60)<I55,IF((I55-SUM(E60:U60))<I55/C53,I55-SUM(E60:U60),I55/C53),0) -> 0 | W60: =IF(SUM(E60:V60)<I55,IF((I55-SUM(E60:V60))<I55/C53,I55-SUM(E60:V60),I55/C53),0) -> 0 | X60: =IF(SUM(E60:W60)<I55,IF((I55-SUM(E60:W60))<I55/C53,I55-SUM(E60:W60),I55/C53),0) -> 0
B61: 第六年投资在各年的折旧 | D61: =SUM(E61:X61) -> 0 | J61: =K61*(1-J54/12) -> 0 | K61: =J55/C53 -> 0 | L61: =IF(SUM(E61:K61)<J55,IF((J55-SUM(E61:K61))<J55/C53,J55-SUM(E61:K61),J55/C53),0) -> 0 | M61: =IF(SUM(E61:L61)<J55,IF((J55-SUM(E61:L61))<J55/C53,J55-SUM(E61:L61),J55/C53),0) -> 0 | N61: =IF(SUM(E61:M61)<J55,IF((J55-SUM(E61:M61))<J55/C53,J55-SUM(E61:M61),J55/C53),0) -> 0 | O61: =IF(SUM(E61:N61)<J55,IF((J55-SUM(E61:N61))<J55/C53,J55-SUM(E61:N61),J55/C53),0) -> 0 | P61: =IF(SUM(E61:O61)<J55,IF((J55-SUM(E61:O61))<J55/C53,J55-SUM(E61:O61),J55/C53),0) -> 0 | Q61: =IF(SUM(E61:P61)<J55,IF((J55-SUM(E61:P61))<J55/C53,J55-SUM(E61:P61),J55/C53),0) -> 0 | R61: =IF(SUM(E61:Q61)<J55,IF((J55-SUM(E61:Q61))<J55/C53,J55-SUM(E61:Q61),J55/C53),0) -> 0 | S61: =IF(SUM(E61:R61)<J55,IF((J55-SUM(E61:R61))<J55/C53,J55-SUM(E61:R61),J55/C53),0) -> 0 | T61: =IF(SUM(E61:S61)<J55,IF((J55-SUM(E61:S61))<J55/C53,J55-SUM(E61:S61),J55/C53),0) -> 0 | U61: =IF(SUM(E61:T61)<J55,IF((J55-SUM(E61:T61))<J55/C53,J55-SUM(E61:T61),J55/C53),0) -> 0 | V61: =IF(SUM(E61:U61)<J55,IF((J55-SUM(E61:U61))<J55/C53,J55-SUM(E61:U61),J55/C53),0) -> 0 | W61: =IF(SUM(E61:V61)<J55,IF((J55-SUM(E61:V61))<J55/C53,J55-SUM(E61:V61),J55/C53),0) -> 0 | X61: =IF(SUM(E61:W61)<J55,IF((J55-SUM(E61:W61))<J55/C53,J55-SUM(E61:W61),J55/C53),0) -> 0
B62: 第七年投资在各年的折旧 | D62: =SUM(E62:X62) -> 0 | K62: =L62*(1-K54/12) -> 0 | L62: =K55/C53 -> 0 | M62: =IF(SUM(E62:L62)<K55,IF((K55-SUM(E62:L62))<K55/C53,K55-SUM(E62:L62),K55/C53),0) -> 0 | N62: =IF(SUM(E62:M62)<K55,IF((K55-SUM(E62:M62))<K55/C53,K55-SUM(E62:M62),K55/C53),0) -> 0 | O62: =IF(SUM(E62:N62)<K55,IF((K55-SUM(E62:N62))<K55/C53,K55-SUM(E62:N62),K55/C53),0) -> 0 | P62: =IF(SUM(E62:O62)<K55,IF((K55-SUM(E62:O62))<K55/C53,K55-SUM(E62:O62),K55/C53),0) -> 0 | Q62: =IF(SUM(E62:P62)<K55,IF((K55-SUM(E62:P62))<K55/C53,K55-SUM(E62:P62),K55/C53),0) -> 0 | R62: =IF(SUM(E62:Q62)<K55,IF((K55-SUM(E62:Q62))<K55/C53,K55-SUM(E62:Q62),K55/C53),0) -> 0 | S62: =IF(SUM(E62:R62)<K55,IF((K55-SUM(E62:R62))<K55/C53,K55-SUM(E62:R62),K55/C53),0) -> 0 | T62: =IF(SUM(E62:S62)<K55,IF((K55-SUM(E62:S62))<K55/C53,K55-SUM(E62:S62),K55/C53),0) -> 0 | U62: =IF(SUM(E62:T62)<K55,IF((K55-SUM(E62:T62))<K55/C53,K55-SUM(E62:T62),K55/C53),0) -> 0 | V62: =IF(SUM(E62:U62)<K55,IF((K55-SUM(E62:U62))<K55/C53,K55-SUM(E62:U62),K55/C53),0) -> 0 | W62: =IF(SUM(E62:V62)<K55,IF((K55-SUM(E62:V62))<K55/C53,K55-SUM(E62:V62),K55/C53),0) -> 0 | X62: =IF(SUM(E62:W62)<K55,IF((K55-SUM(E62:W62))<K55/C53,K55-SUM(E62:W62),K55/C53),0) -> 0
B63: 第八年投资在各年的折旧 | D63: =SUM(E63:X63) -> 0 | L63: =M63*(1-L54/12) -> 0 | M63: =L55/C53 -> 0 | N63: =IF(SUM(E63:M63)<L55,IF((L55-SUM(E63:M63))<L55/C53,L55-SUM(E63:M63),L55/C53),0) -> 0 | O63: =IF(SUM(E63:N63)<L55,IF((L55-SUM(E63:N63))<L55/C53,L55-SUM(E63:N63),L55/C53),0) -> 0 | P63: =IF(SUM(E63:O63)<L55,IF((L55-SUM(E63:O63))<L55/C53,L55-SUM(E63:O63),L55/C53),0) -> 0 | Q63: =IF(SUM(E63:P63)<L55,IF((L55-SUM(E63:P63))<L55/C53,L55-SUM(E63:P63),L55/C53),0) -> 0 | R63: =IF(SUM(E63:Q63)<L55,IF((L55-SUM(E63:Q63))<L55/C53,L55-SUM(E63:Q63),L55/C53),0) -> 0 | S63: =IF(SUM(E63:R63)<L55,IF((L55-SUM(E63:R63))<L55/C53,L55-SUM(E63:R63),L55/C53),0) -> 0 | T63: =IF(SUM(E63:S63)<L55,IF((L55-SUM(E63:S63))<L55/C53,L55-SUM(E63:S63),L55/C53),0) -> 0 | U63: =IF(SUM(E63:T63)<L55,IF((L55-SUM(E63:T63))<L55/C53,L55-SUM(E63:T63),L55/C53),0) -> 0 | V63: =IF(SUM(E63:U63)<L55,IF((L55-SUM(E63:U63))<L55/C53,L55-SUM(E63:U63),L55/C53),0) -> 0 | W63: =IF(SUM(E63:V63)<L55,IF((L55-SUM(E63:V63))<L55/C53,L55-SUM(E63:V63),L55/C53),0) -> 0 | X63: =IF(SUM(E63:W63)<L55,IF((L55-SUM(E63:W63))<L55/C53,L55-SUM(E63:W63),L55/C53),0) -> 0
B64: 第九年投资在各年的折旧 | D64: =SUM(E64:X64) -> 0 | M64: =N64*(1-M54/12) -> 0 | N64: =M55/C53 -> 0 | O64: =IF(SUM(E64:N64)<M55,IF((M55-SUM(E64:N64))<M55/C53,M55-SUM(E64:N64),M55/C53),0) -> 0 | P64: =IF(SUM(E64:O64)<M55,IF((M55-SUM(E64:O64))<M55/C53,M55-SUM(E64:O64),M55/C53),0) -> 0 | Q64: =IF(SUM(E64:P64)<M55,IF((M55-SUM(E64:P64))<M55/C53,M55-SUM(E64:P64),M55/C53),0) -> 0 | R64: =IF(SUM(E64:Q64)<M55,IF((M55-SUM(E64:Q64))<M55/C53,M55-SUM(E64:Q64),M55/C53),0) -> 0 | S64: =IF(SUM(E64:R64)<M55,IF((M55-SUM(E64:R64))<M55/C53,M55-SUM(E64:R64),M55/C53),0) -> 0 | T64: =IF(SUM(E64:S64)<M55,IF((M55-SUM(E64:S64))<M55/C53,M55-SUM(E64:S64),M55/C53),0) -> 0 | U64: =IF(SUM(E64:T64)<M55,IF((M55-SUM(E64:T64))<M55/C53,M55-SUM(E64:T64),M55/C53),0) -> 0 | V64: =IF(SUM(E64:U64)<M55,IF((M55-SUM(E64:U64))<M55/C53,M55-SUM(E64:U64),M55/C53),0) -> 0 | W64: =IF(SUM(E64:V64)<M55,IF((M55-SUM(E64:V64))<M55/C53,M55-SUM(E64:V64),M55/C53),0) -> 0 | X64: =IF(SUM(E64:W64)<M55,IF((M55-SUM(E64:W64))<M55/C53,M55-SUM(E64:W64),M55/C53),0) -> 0
B65: 第十年投资在各年的折旧 | D65: =SUM(E65:X65) -> 0 | N65: =O65*(1-N54/12) -> 0 | O65: =N55/C53 -> 0 | P65: =IF(SUM(E65:O65)<N55,IF((N55-SUM(E65:O65))<N55/C53,N55-SUM(E65:O65),N55/C53),0) -> 0 | Q65: =IF(SUM(E65:P65)<N55,IF((N55-SUM(E65:P65))<N55/C53,N55-SUM(E65:P65),N55/C53),0) -> 0 | R65: =IF(SUM(E65:Q65)<N55,IF((N55-SUM(E65:Q65))<N55/C53,N55-SUM(E65:Q65),N55/C53),0) -> 0 | S65: =IF(SUM(E65:R65)<N55,IF((N55-SUM(E65:R65))<N55/C53,N55-SUM(E65:R65),N55/C53),0) -> 0 | T65: =IF(SUM(E65:S65)<N55,IF((N55-SUM(E65:S65))<N55/C53,N55-SUM(E65:S65),N55/C53),0) -> 0 | U65: =IF(SUM(E65:T65)<N55,IF((N55-SUM(E65:T65))<N55/C53,N55-SUM(E65:T65),N55/C53),0) -> 0 | V65: =IF(SUM(E65:U65)<N55,IF((N55-SUM(E65:U65))<N55/C53,N55-SUM(E65:U65),N55/C53),0) -> 0 | W65: =IF(SUM(E65:V65)<N55,IF((N55-SUM(E65:V65))<N55/C53,N55-SUM(E65:V65),N55/C53),0) -> 0 | X65: =IF(SUM(E65:W65)<N55,IF((N55-SUM(E65:W65))<N55/C53,N55-SUM(E65:W65),N55/C53),0) -> 0
B66: 第十一年投资在各年的折旧 | D66: =SUM(E66:X66) -> 0 | O66: =P66*(1-O54/12) -> 0 | P66: =O55/C53 -> 0 | Q66: =IF(SUM(E66:P66)<O55,IF((O55-SUM(E66:P66))<O55/C53,O55-SUM(E66:P66),O55/C53),0) -> 0 | R66: =IF(SUM(E66:Q66)<O55,IF((O55-SUM(E66:Q66))<O55/C53,O55-SUM(E66:Q66),O55/C53),0) -> 0 | S66: =IF(SUM(E66:R66)<O55,IF((O55-SUM(E66:R66))<O55/C53,O55-SUM(E66:R66),O55/C53),0) -> 0 | T66: =IF(SUM(E66:S66)<O55,IF((O55-SUM(E66:S66))<O55/C53,O55-SUM(E66:S66),O55/C53),0) -> 0 | U66: =IF(SUM(E66:T66)<O55,IF((O55-SUM(E66:T66))<O55/C53,O55-SUM(E66:T66),O55/C53),0) -> 0 | V66: =IF(SUM(E66:U66)<O55,IF((O55-SUM(E66:U66))<O55/C53,O55-SUM(E66:U66),O55/C53),0) -> 0 | W66: =IF(SUM(E66:V66)<O55,IF((O55-SUM(E66:V66))<O55/C53,O55-SUM(E66:V66),O55/C53),0) -> 0 | X66: =IF(SUM(E66:W66)<O55,IF((O55-SUM(E66:W66))<O55/C53,O55-SUM(E66:W66),O55/C53),0) -> 0
B68: 其他类投资累计折旧 | D68: =SUM(E68:X68) -> 0 | E68: =SUM(E72:E82) -> 0 | F68: =SUM(F72:F82) -> 0 | G68: =SUM(G72:G82) -> 0 | H68: =SUM(H72:H82) -> 0 | I68: =SUM(I72:I82) -> 0 | J68: =SUM(J72:J82) -> 0 | K68: =SUM(K72:K82) -> 0 | L68: =SUM(L72:L82) -> 0 | ... X68: =SUM(X72:X82) -> 0
B69: 折旧年限 | C69: 5
B70: 当年投产月份 | E70: 0 | F70: 0 | G70: 0 | H70: 0 | I70: 0 | J70: 0 | K70: 0 | L70: 0 | M70: 0 | N70: 0 | O70: 0
B71: 其他类投资规模 | D71: =SUM(E71:O71) -> 0
B72: 第一年投资在各年的折旧 | D72: =SUM(E72:X72) -> 0 | E72: =F72*(1-E70/12) -> 0 | F72: =E71/C69 -> 0 | G72: =IF(SUM(E72:F72)<E71,IF((E71-SUM(E72:F72))<E71/C69,E71-SUM(E72:F72),E71/C69),0) -> 0 | H72: =IF(SUM(E72:G72)<E71,IF((E71-SUM(E72:G72))<E71/C69,E71-SUM(E72:G72),E71/C69),0) -> 0 | I72: =IF(SUM(E72:H72)<E71,IF((E71-SUM(E72:H72))<E71/C69,E71-SUM(E72:H72),E71/C69),0) -> 0 | J72: =IF(SUM(E72:I72)<E71,IF((E71-SUM(E72:I72))<E71/C69,E71-SUM(E72:I72),E71/C69),0) -> 0 | K72: =IF(SUM(E72:J72)<E71,IF((E71-SUM(E72:J72))<E71/C69,E71-SUM(E72:J72),E71/C69),0) -> 0 | L72: =IF(SUM(E72:K72)<E71,IF((E71-SUM(E72:K72))<E71/C69,E71-SUM(E72:K72),E71/C69),0) -> 0 | M72: =IF(SUM(E72:L72)<E71,IF((E71-SUM(E72:L72))<E71/C69,E71-SUM(E72:L72),E71/C69),0) -> 0 | N72: =IF(SUM(E72:M72)<E71,IF((E71-SUM(E72:M72))<E71/C69,E71-SUM(E72:M72),E71/C69),0) -> 0 | O72: =IF(SUM(E72:N72)<E71,IF((E71-SUM(E72:N72))<E71/C69,E71-SUM(E72:N72),E71/C69),0) -> 0 | P72: =IF(SUM(E72:O72)<E71,IF((E71-SUM(E72:O72))<E71/C69,E71-SUM(E72:O72),E71/C69),0) -> 0 | Q72: =IF(SUM(E72:P72)<E71,IF((E71-SUM(E72:P72))<E71/C69,E71-SUM(E72:P72),E71/C69),0) -> 0 | R72: =IF(SUM(E72:Q72)<E71,IF((E71-SUM(E72:Q72))<E71/C69,E71-SUM(E72:Q72),E71/C69),0) -> 0 | S72: =IF(SUM(E72:R72)<E71,IF((E71-SUM(E72:R72))<E71/C69,E71-SUM(E72:R72),E71/C69),0) -> 0 | T72: =IF(SUM(E72:S72)<E71,IF((E71-SUM(E72:S72))<E71/C69,E71-SUM(E72:S72),E71/C69),0) -> 0 | U72: =IF(SUM(E72:T72)<E71,IF((E71-SUM(E72:T72))<E71/C69,E71-SUM(E72:T72),E71/C69),0) -> 0 | V72: =IF(SUM(E72:U72)<E71,IF((E71-SUM(E72:U72))<E71/C69,E71-SUM(E72:U72),E71/C69),0) -> 0 | W72: =IF(SUM(E72:V72)<E71,IF((E71-SUM(E72:V72))<E71/C69,E71-SUM(E72:V72),E71/C69),0) -> 0 | X72: =IF(SUM(E72:W72)<E71,IF((E71-SUM(E72:W72))<E71/C69,E71-SUM(E72:W72),E71/C69),0) -> 0
B73: 第二年投资在各年的折旧 | D73: =SUM(E73:X73) -> 0 | F73: =G73*(1-F70/12) -> 0 | G73: =F71/C69 -> 0 | H73: =IF(SUM(E73:G73)<F71,IF((F71-SUM(E73:G73))<F71/C69,F71-SUM(E73:G73),F71/C69),0) -> 0 | I73: =IF(SUM(E73:H73)<F71,IF((F71-SUM(E73:H73))<F71/C69,F71-SUM(E73:H73),F71/C69),0) -> 0 | J73: =IF(SUM(E73:I73)<F71,IF((F71-SUM(E73:I73))<F71/C69,F71-SUM(E73:I73),F71/C69),0) -> 0 | K73: =IF(SUM(E73:J73)<F71,IF((F71-SUM(E73:J73))<F71/C69,F71-SUM(E73:J73),F71/C69),0) -> 0 | L73: =IF(SUM(E73:K73)<F71,IF((F71-SUM(E73:K73))<F71/C69,F71-SUM(E73:K73),F71/C69),0) -> 0 | M73: =IF(SUM(E73:L73)<F71,IF((F71-SUM(E73:L73))<F71/C69,F71-SUM(E73:L73),F71/C69),0) -> 0 | N73: =IF(SUM(E73:M73)<F71,IF((F71-SUM(E73:M73))<F71/C69,F71-SUM(E73:M73),F71/C69),0) -> 0 | O73: =IF(SUM(E73:N73)<F71,IF((F71-SUM(E73:N73))<F71/C69,F71-SUM(E73:N73),F71/C69),0) -> 0 | P73: =IF(SUM(E73:O73)<F71,IF((F71-SUM(E73:O73))<F71/C69,F71-SUM(E73:O73),F71/C69),0) -> 0 | Q73: =IF(SUM(E73:P73)<F71,IF((F71-SUM(E73:P73))<F71/C69,F71-SUM(E73:P73),F71/C69),0) -> 0 | R73: =IF(SUM(E73:Q73)<F71,IF((F71-SUM(E73:Q73))<F71/C69,F71-SUM(E73:Q73),F71/C69),0) -> 0 | S73: =IF(SUM(E73:R73)<F71,IF((F71-SUM(E73:R73))<F71/C69,F71-SUM(E73:R73),F71/C69),0) -> 0 | T73: =IF(SUM(E73:S73)<F71,IF((F71-SUM(E73:S73))<F71/C69,F71-SUM(E73:S73),F71/C69),0) -> 0 | U73: =IF(SUM(E73:T73)<F71,IF((F71-SUM(E73:T73))<F71/C69,F71-SUM(E73:T73),F71/C69),0) -> 0 | V73: =IF(SUM(E73:U73)<F71,IF((F71-SUM(E73:U73))<F71/C69,F71-SUM(E73:U73),F71/C69),0) -> 0 | W73: =IF(SUM(E73:V73)<F71,IF((F71-SUM(E73:V73))<F71/C69,F71-SUM(E73:V73),F71/C69),0) -> 0 | X73: =IF(SUM(E73:W73)<F71,IF((F71-SUM(E73:W73))<F71/C69,F71-SUM(E73:W73),F71/C69),0) -> 0
B74: 第三年投资在各年的折旧 | D74: =SUM(E74:X74) -> 0 | G74: =H74*(1-G70/12) -> 0 | H74: =G71/C69 -> 0 | I74: =IF(SUM(E74:H74)<G71,IF((G71-SUM(E74:H74))<G71/C69,G71-SUM(E74:H74),G71/C69),0) -> 0 | J74: =IF(SUM(E74:I74)<G71,IF((G71-SUM(E74:I74))<G71/C69,G71-SUM(E74:I74),G71/C69),0) -> 0 | K74: =IF(SUM(E74:J74)<G71,IF((G71-SUM(E74:J74))<G71/C69,G71-SUM(E74:J74),G71/C69),0) -> 0 | L74: =IF(SUM(E74:K74)<G71,IF((G71-SUM(E74:K74))<G71/C69,G71-SUM(E74:K74),G71/C69),0) -> 0 | M74: =IF(SUM(E74:L74)<G71,IF((G71-SUM(E74:L74))<G71/C69,G71-SUM(E74:L74),G71/C69),0) -> 0 | N74: =IF(SUM(E74:M74)<G71,IF((G71-SUM(E74:M74))<G71/C69,G71-SUM(E74:M74),G71/C69),0) -> 0 | O74: =IF(SUM(E74:N74)<G71,IF((G71-SUM(E74:N74))<G71/C69,G71-SUM(E74:N74),G71/C69),0) -> 0 | P74: =IF(SUM(E74:O74)<G71,IF((G71-SUM(E74:O74))<G71/C69,G71-SUM(E74:O74),G71/C69),0) -> 0 | Q74: =IF(SUM(E74:P74)<G71,IF((G71-SUM(E74:P74))<G71/C69,G71-SUM(E74:P74),G71/C69),0) -> 0 | R74: =IF(SUM(E74:Q74)<G71,IF((G71-SUM(E74:Q74))<G71/C69,G71-SUM(E74:Q74),G71/C69),0) -> 0 | S74: =IF(SUM(E74:R74)<G71,IF((G71-SUM(E74:R74))<G71/C69,G71-SUM(E74:R74),G71/C69),0) -> 0 | T74: =IF(SUM(E74:S74)<G71,IF((G71-SUM(E74:S74))<G71/C69,G71-SUM(E74:S74),G71/C69),0) -> 0 | U74: =IF(SUM(E74:T74)<G71,IF((G71-SUM(E74:T74))<G71/C69,G71-SUM(E74:T74),G71/C69),0) -> 0 | V74: =IF(SUM(E74:U74)<G71,IF((G71-SUM(E74:U74))<G71/C69,G71-SUM(E74:U74),G71/C69),0) -> 0 | W74: =IF(SUM(E74:V74)<G71,IF((G71-SUM(E74:V74))<G71/C69,G71-SUM(E74:V74),G71/C69),0) -> 0 | X74: =IF(SUM(E74:W74)<G71,IF((G71-SUM(E74:W74))<G71/C69,G71-SUM(E74:W74),G71/C69),0) -> 0
B75: 第四年投资在各年的折旧 | D75: =SUM(E75:X75) -> 0 | H75: =I75*(1-H70/12) -> 0 | I75: =H71/C69 -> 0 | J75: =IF(SUM(E75:I75)<H71,IF((H71-SUM(E75:I75))<H71/C69,H71-SUM(E75:I75),H71/C69),0) -> 0 | K75: =IF(SUM(E75:J75)<H71,IF((H71-SUM(E75:J75))<H71/C69,H71-SUM(E75:J75),H71/C69),0) -> 0 | L75: =IF(SUM(E75:K75)<H71,IF((H71-SUM(E75:K75))<H71/C69,H71-SUM(E75:K75),H71/C69),0) -> 0 | M75: =IF(SUM(E75:L75)<H71,IF((H71-SUM(E75:L75))<H71/C69,H71-SUM(E75:L75),H71/C69),0) -> 0 | N75: =IF(SUM(E75:M75)<H71,IF((H71-SUM(E75:M75))<H71/C69,H71-SUM(E75:M75),H71/C69),0) -> 0 | O75: =IF(SUM(E75:N75)<H71,IF((H71-SUM(E75:N75))<H71/C69,H71-SUM(E75:N75),H71/C69),0) -> 0 | P75: =IF(SUM(E75:O75)<H71,IF((H71-SUM(E75:O75))<H71/C69,H71-SUM(E75:O75),H71/C69),0) -> 0 | Q75: =IF(SUM(E75:P75)<H71,IF((H71-SUM(E75:P75))<H71/C69,H71-SUM(E75:P75),H71/C69),0) -> 0 | R75: =IF(SUM(E75:Q75)<H71,IF((H71-SUM(E75:Q75))<H71/C69,H71-SUM(E75:Q75),H71/C69),0) -> 0 | S75: =IF(SUM(E75:R75)<H71,IF((H71-SUM(E75:R75))<H71/C69,H71-SUM(E75:R75),H71/C69),0) -> 0 | T75: =IF(SUM(E75:S75)<H71,IF((H71-SUM(E75:S75))<H71/C69,H71-SUM(E75:S75),H71/C69),0) -> 0 | U75: =IF(SUM(E75:T75)<H71,IF((H71-SUM(E75:T75))<H71/C69,H71-SUM(E75:T75),H71/C69),0) -> 0 | V75: =IF(SUM(E75:U75)<H71,IF((H71-SUM(E75:U75))<H71/C69,H71-SUM(E75:U75),H71/C69),0) -> 0 | W75: =IF(SUM(E75:V75)<H71,IF((H71-SUM(E75:V75))<H71/C69,H71-SUM(E75:V75),H71/C69),0) -> 0 | X75: =IF(SUM(E75:W75)<H71,IF((H71-SUM(E75:W75))<H71/C69,H71-SUM(E75:W75),H71/C69),0) -> 0
B76: 第五年投资在各年的折旧 | D76: =SUM(E76:X76) -> 0 | I76: =J76*(1-I70/12) -> 0 | J76: =I71/C69 -> 0 | K76: =IF(SUM(E76:J76)<I71,IF((I71-SUM(E76:J76))<I71/C69,I71-SUM(E76:J76),I71/C69),0) -> 0 | L76: =IF(SUM(E76:K76)<I71,IF((I71-SUM(E76:K76))<I71/C69,I71-SUM(E76:K76),I71/C69),0) -> 0 | M76: =IF(SUM(E76:L76)<I71,IF((I71-SUM(E76:L76))<I71/C69,I71-SUM(E76:L76),I71/C69),0) -> 0 | N76: =IF(SUM(E76:M76)<I71,IF((I71-SUM(E76:M76))<I71/C69,I71-SUM(E76:M76),I71/C69),0) -> 0 | O76: =IF(SUM(E76:N76)<I71,IF((I71-SUM(E76:N76))<I71/C69,I71-SUM(E76:N76),I71/C69),0) -> 0 | P76: =IF(SUM(E76:O76)<I71,IF((I71-SUM(E76:O76))<I71/C69,I71-SUM(E76:O76),I71/C69),0) -> 0 | Q76: =IF(SUM(E76:P76)<I71,IF((I71-SUM(E76:P76))<I71/C69,I71-SUM(E76:P76),I71/C69),0) -> 0 | R76: =IF(SUM(E76:Q76)<I71,IF((I71-SUM(E76:Q76))<I71/C69,I71-SUM(E76:Q76),I71/C69),0) -> 0 | S76: =IF(SUM(E76:R76)<I71,IF((I71-SUM(E76:R76))<I71/C69,I71-SUM(E76:R76),I71/C69),0) -> 0 | T76: =IF(SUM(E76:S76)<I71,IF((I71-SUM(E76:S76))<I71/C69,I71-SUM(E76:S76),I71/C69),0) -> 0 | U76: =IF(SUM(E76:T76)<I71,IF((I71-SUM(E76:T76))<I71/C69,I71-SUM(E76:T76),I71/C69),0) -> 0 | V76: =IF(SUM(E76:U76)<I71,IF((I71-SUM(E76:U76))<I71/C69,I71-SUM(E76:U76),I71/C69),0) -> 0 | W76: =IF(SUM(E76:V76)<I71,IF((I71-SUM(E76:V76))<I71/C69,I71-SUM(E76:V76),I71/C69),0) -> 0 | X76: =IF(SUM(E76:W76)<I71,IF((I71-SUM(E76:W76))<I71/C69,I71-SUM(E76:W76),I71/C69),0) -> 0
B77: 第六年投资在各年的折旧 | D77: =SUM(E77:X77) -> 0 | J77: =K77*(1-J70/12) -> 0 | K77: =J71/C69 -> 0 | L77: =IF(SUM(E77:K77)<J71,IF((J71-SUM(E77:K77))<J71/C69,J71-SUM(E77:K77),J71/C69),0) -> 0 | M77: =IF(SUM(E77:L77)<J71,IF((J71-SUM(E77:L77))<J71/C69,J71-SUM(E77:L77),J71/C69),0) -> 0 | N77: =IF(SUM(E77:M77)<J71,IF((J71-SUM(E77:M77))<J71/C69,J71-SUM(E77:M77),J71/C69),0) -> 0 | O77: =IF(SUM(E77:N77)<J71,IF((J71-SUM(E77:N77))<J71/C69,J71-SUM(E77:N77),J71/C69),0) -> 0 | P77: =IF(SUM(E77:O77)<J71,IF((J71-SUM(E77:O77))<J71/C69,J71-SUM(E77:O77),J71/C69),0) -> 0 | Q77: =IF(SUM(E77:P77)<J71,IF((J71-SUM(E77:P77))<J71/C69,J71-SUM(E77:P77),J71/C69),0) -> 0 | R77: =IF(SUM(E77:Q77)<J71,IF((J71-SUM(E77:Q77))<J71/C69,J71-SUM(E77:Q77),J71/C69),0) -> 0 | S77: =IF(SUM(E77:R77)<J71,IF((J71-SUM(E77:R77))<J71/C69,J71-SUM(E77:R77),J71/C69),0) -> 0 | T77: =IF(SUM(E77:S77)<J71,IF((J71-SUM(E77:S77))<J71/C69,J71-SUM(E77:S77),J71/C69),0) -> 0 | U77: =IF(SUM(E77:T77)<J71,IF((J71-SUM(E77:T77))<J71/C69,J71-SUM(E77:T77),J71/C69),0) -> 0 | V77: =IF(SUM(E77:U77)<J71,IF((J71-SUM(E77:U77))<J71/C69,J71-SUM(E77:U77),J71/C69),0) -> 0 | W77: =IF(SUM(E77:V77)<J71,IF((J71-SUM(E77:V77))<J71/C69,J71-SUM(E77:V77),J71/C69),0) -> 0 | X77: =IF(SUM(E77:W77)<J71,IF((J71-SUM(E77:W77))<J71/C69,J71-SUM(E77:W77),J71/C69),0) -> 0
B78: 第七年投资在各年的折旧 | D78: =SUM(E78:X78) -> 0 | K78: =L78*(1-K70/12) -> 0 | L78: =K71/C69 -> 0 | M78: =IF(SUM(E78:L78)<K71,IF((K71-SUM(E78:L78))<K71/C69,K71-SUM(E78:L78),K71/C69),0) -> 0 | N78: =IF(SUM(E78:M78)<K71,IF((K71-SUM(E78:M78))<K71/C69,K71-SUM(E78:M78),K71/C69),0) -> 0 | O78: =IF(SUM(E78:N78)<K71,IF((K71-SUM(E78:N78))<K71/C69,K71-SUM(E78:N78),K71/C69),0) -> 0 | P78: =IF(SUM(E78:O78)<K71,IF((K71-SUM(E78:O78))<K71/C69,K71-SUM(E78:O78),K71/C69),0) -> 0 | Q78: =IF(SUM(E78:P78)<K71,IF((K71-SUM(E78:P78))<K71/C69,K71-SUM(E78:P78),K71/C69),0) -> 0 | R78: =IF(SUM(E78:Q78)<K71,IF((K71-SUM(E78:Q78))<K71/C69,K71-SUM(E78:Q78),K71/C69),0) -> 0 | S78: =IF(SUM(E78:R78)<K71,IF((K71-SUM(E78:R78))<K71/C69,K71-SUM(E78:R78),K71/C69),0) -> 0 | T78: =IF(SUM(E78:S78)<K71,IF((K71-SUM(E78:S78))<K71/C69,K71-SUM(E78:S78),K71/C69),0) -> 0 | U78: =IF(SUM(E78:T78)<K71,IF((K71-SUM(E78:T78))<K71/C69,K71-SUM(E78:T78),K71/C69),0) -> 0 | V78: =IF(SUM(E78:U78)<K71,IF((K71-SUM(E78:U78))<K71/C69,K71-SUM(E78:U78),K71/C69),0) -> 0 | W78: =IF(SUM(E78:V78)<K71,IF((K71-SUM(E78:V78))<K71/C69,K71-SUM(E78:V78),K71/C69),0) -> 0 | X78: =IF(SUM(E78:W78)<K71,IF((K71-SUM(E78:W78))<K71/C69,K71-SUM(E78:W78),K71/C69),0) -> 0
B79: 第八年投资在各年的折旧 | D79: =SUM(E79:X79) -> 0 | L79: =M79*(1-L70/12) -> 0 | M79: =L71/C69 -> 0 | N79: =IF(SUM(E79:M79)<L71,IF((L71-SUM(E79:M79))<L71/C69,L71-SUM(E79:M79),L71/C69),0) -> 0 | O79: =IF(SUM(E79:N79)<L71,IF((L71-SUM(E79:N79))<L71/C69,L71-SUM(E79:N79),L71/C69),0) -> 0 | P79: =IF(SUM(E79:O79)<L71,IF((L71-SUM(E79:O79))<L71/C69,L71-SUM(E79:O79),L71/C69),0) -> 0 | Q79: =IF(SUM(E79:P79)<L71,IF((L71-SUM(E79:P79))<L71/C69,L71-SUM(E79:P79),L71/C69),0) -> 0 | R79: =IF(SUM(E79:Q79)<L71,IF((L71-SUM(E79:Q79))<L71/C69,L71-SUM(E79:Q79),L71/C69),0) -> 0 | S79: =IF(SUM(E79:R79)<L71,IF((L71-SUM(E79:R79))<L71/C69,L71-SUM(E79:R79),L71/C69),0) -> 0 | T79: =IF(SUM(E79:S79)<L71,IF((L71-SUM(E79:S79))<L71/C69,L71-SUM(E79:S79),L71/C69),0) -> 0 | U79: =IF(SUM(E79:T79)<L71,IF((L71-SUM(E79:T79))<L71/C69,L71-SUM(E79:T79),L71/C69),0) -> 0 | V79: =IF(SUM(E79:U79)<L71,IF((L71-SUM(E79:U79))<L71/C69,L71-SUM(E79:U79),L71/C69),0) -> 0 | W79: =IF(SUM(E79:V79)<L71,IF((L71-SUM(E79:V79))<L71/C69,L71-SUM(E79:V79),L71/C69),0) -> 0 | X79: =IF(SUM(E79:W79)<L71,IF((L71-SUM(E79:W79))<L71/C69,L71-SUM(E79:W79),L71/C69),0) -> 0
B80: 第九年投资在各年的折旧 | D80: =SUM(E80:X80) -> 0 | M80: =N80*(1-M70/12) -> 0 | N80: =M71/C69 -> 0 | O80: =IF(SUM(E80:N80)<M71,IF((M71-SUM(E80:N80))<M71/C69,M71-SUM(E80:N80),M71/C69),0) -> 0 | P80: =IF(SUM(E80:O80)<M71,IF((M71-SUM(E80:O80))<M71/C69,M71-SUM(E80:O80),M71/C69),0) -> 0 | Q80: =IF(SUM(E80:P80)<M71,IF((M71-SUM(E80:P80))<M71/C69,M71-SUM(E80:P80),M71/C69),0) -> 0 | R80: =IF(SUM(E80:Q80)<M71,IF((M71-SUM(E80:Q80))<M71/C69,M71-SUM(E80:Q80),M71/C69),0) -> 0 | S80: =IF(SUM(E80:R80)<M71,IF((M71-SUM(E80:R80))<M71/C69,M71-SUM(E80:R80),M71/C69),0) -> 0 | T80: =IF(SUM(E80:S80)<M71,IF((M71-SUM(E80:S80))<M71/C69,M71-SUM(E80:S80),M71/C69),0) -> 0 | U80: =IF(SUM(E80:T80)<M71,IF((M71-SUM(E80:T80))<M71/C69,M71-SUM(E80:T80),M71/C69),0) -> 0 | V80: =IF(SUM(E80:U80)<M71,IF((M71-SUM(E80:U80))<M71/C69,M71-SUM(E80:U80),M71/C69),0) -> 0 | W80: =IF(SUM(E80:V80)<M71,IF((M71-SUM(E80:V80))<M71/C69,M71-SUM(E80:V80),M71/C69),0) -> 0 | X80: =IF(SUM(E80:W80)<M71,IF((M71-SUM(E80:W80))<M71/C69,M71-SUM(E80:W80),M71/C69),0) -> 0
B81: 第十年投资在各年的折旧 | D81: =SUM(E81:X81) -> 0 | N81: =O81*(1-N70/12) -> 0 | O81: =N71/C69 -> 0 | P81: =IF(SUM(E81:O81)<N71,IF((N71-SUM(E81:O81))<N71/C69,N71-SUM(E81:O81),N71/C69),0) -> 0 | Q81: =IF(SUM(E81:P81)<N71,IF((N71-SUM(E81:P81))<N71/C69,N71-SUM(E81:P81),N71/C69),0) -> 0 | R81: =IF(SUM(E81:Q81)<N71,IF((N71-SUM(E81:Q81))<N71/C69,N71-SUM(E81:Q81),N71/C69),0) -> 0 | S81: =IF(SUM(E81:R81)<N71,IF((N71-SUM(E81:R81))<N71/C69,N71-SUM(E81:R81),N71/C69),0) -> 0 | T81: =IF(SUM(E81:S81)<N71,IF((N71-SUM(E81:S81))<N71/C69,N71-SUM(E81:S81),N71/C69),0) -> 0 | U81: =IF(SUM(E81:T81)<N71,IF((N71-SUM(E81:T81))<N71/C69,N71-SUM(E81:T81),N71/C69),0) -> 0 | V81: =IF(SUM(E81:U81)<N71,IF((N71-SUM(E81:U81))<N71/C69,N71-SUM(E81:U81),N71/C69),0) -> 0 | W81: =IF(SUM(E81:V81)<N71,IF((N71-SUM(E81:V81))<N71/C69,N71-SUM(E81:V81),N71/C69),0) -> 0 | X81: =IF(SUM(E81:W81)<N71,IF((N71-SUM(E81:W81))<N71/C69,N71-SUM(E81:W81),N71/C69),0) -> 0
B82: 第十一年投资在各年的折旧 | D82: =SUM(E82:X82) -> 0 | O82: =P82*(1-O70/12) -> 0 | P82: =O71/C69 -> 0 | Q82: =IF(SUM(E82:P82)<O71,IF((O71-SUM(E82:P82))<O71/C69,O71-SUM(E82:P82),O71/C69),0) -> 0 | R82: =IF(SUM(E82:Q82)<O71,IF((O71-SUM(E82:Q82))<O71/C69,O71-SUM(E82:Q82),O71/C69),0) -> 0 | S82: =IF(SUM(E82:R82)<O71,IF((O71-SUM(E82:R82))<O71/C69,O71-SUM(E82:R82),O71/C69),0) -> 0 | T82: =IF(SUM(E82:S82)<O71,IF((O71-SUM(E82:S82))<O71/C69,O71-SUM(E82:S82),O71/C69),0) -> 0 | U82: =IF(SUM(E82:T82)<O71,IF((O71-SUM(E82:T82))<O71/C69,O71-SUM(E82:T82),O71/C69),0) -> 0 | V82: =IF(SUM(E82:U82)<O71,IF((O71-SUM(E82:U82))<O71/C69,O71-SUM(E82:U82),O71/C69),0) -> 0 | W82: =IF(SUM(E82:V82)<O71,IF((O71-SUM(E82:V82))<O71/C69,O71-SUM(E82:V82),O71/C69),0) -> 0 | X82: =IF(SUM(E82:W82)<O71,IF((O71-SUM(E82:W82))<O71/C69,O71-SUM(E82:W82),O71/C69),0) -> 0
